{
  "eval_id": 0,
  "eval_name": "pr-22214-large-frontend-refactor",
  "config": "no_skill",
  "expectations": [
    {"text": "Review includes a complexity/split advisory for the large 75+ file scope", "passed": true, "evidence": "Issue #5 flags massive reformatting of UiBaseLocators.ts mixed with functional changes"},
    {"text": "Review identifies deprecation patterns (@deprecated, UmbDeprecation)", "passed": true, "evidence": "Backwards Compatibility section discusses @deprecated JSDoc and UmbDeprecation warnings"},
    {"text": "Checks frontend-specific breaking changes (exports, custom elements) not just backend", "passed": true, "evidence": "Issues #1 and #6 flag alias renames and deleted action classes"},
    {"text": "Findings reference specific files with line numbers", "passed": true, "evidence": "All issues reference specific file paths"},
    {"text": "Properly deprecated code is NOT flagged as Critical breaking change", "passed": true, "evidence": "Deprecated modals noted as properly handled"},
    {"text": "Review does not flag purely cosmetic/stylistic issues unless they affect performance or rendering", "passed": false, "evidence": "Issue #4 flags ellipsis localization (i18n concern but largely cosmetic) and Issue #7 flags test locator fragility (pre-existing pattern)"}
  ]
}
