<?xml version="1.0" encoding="utf-8"?>
<!-- https://learn.microsoft.com/en-us/dotnet/fundamentals/package-validation/diagnostic-ids -->
<Suppressions xmlns:xsi="http://www.w3.org/2001/XMLSchema-instance" xmlns:xsd="http://www.w3.org/2001/XMLSchema">
  <Suppression>
    <DiagnosticId>CP0001</DiagnosticId>
    <Target>T:Umbraco.Cms.Core.IO.IManifestFileProviderFactory</Target>
    <Left>lib/net7.0/Umbraco.Core.dll</Left>
    <Right>lib/net7.0/Umbraco.Core.dll</Right>
    <IsBaselineSuppression>true</IsBaselineSuppression>
  </Suppression>
  <Suppression>
    <DiagnosticId>CP0001</DiagnosticId>
    <Target>T:Umbraco.Cms.Core.Manifest.CompositePackageManifest</Target>
    <Left>lib/net7.0/Umbraco.Core.dll</Left>
    <Right>lib/net7.0/Umbraco.Core.dll</Right>
    <IsBaselineSuppression>true</IsBaselineSuppression>
  </Suppression>
  <Suppression>
    <DiagnosticId>CP0001</DiagnosticId>
    <Target>T:Umbraco.Cms.Core.Manifest.IManifestFilter</Target>
    <Left>lib/net7.0/Umbraco.Core.dll</Left>
    <Right>lib/net7.0/Umbraco.Core.dll</Right>
    <IsBaselineSuppression>true</IsBaselineSuppression>
  </Suppression>
  <Suppression>
    <DiagnosticId>CP0001</DiagnosticId>
    <Target>T:Umbraco.Cms.Core.Manifest.IManifestParser</Target>
    <Left>lib/net7.0/Umbraco.Core.dll</Left>
    <Right>lib/net7.0/Umbraco.Core.dll</Right>
    <IsBaselineSuppression>true</IsBaselineSuppression>
  </Suppression>
  <Suppression>
    <DiagnosticId>CP0001</DiagnosticId>
    <Target>T:Umbraco.Cms.Core.Manifest.IPackageManifest</Target>
    <Left>lib/net7.0/Umbraco.Core.dll</Left>
    <Right>lib/net7.0/Umbraco.Core.dll</Right>
    <IsBaselineSuppression>true</IsBaselineSuppression>
  </Suppression>
  <Suppression>
    <DiagnosticId>CP0001</DiagnosticId>
    <Target>T:Umbraco.Cms.Core.Manifest.ManifestAssets</Target>
    <Left>lib/net7.0/Umbraco.Core.dll</Left>
    <Right>lib/net7.0/Umbraco.Core.dll</Right>
    <IsBaselineSuppression>true</IsBaselineSuppression>
  </Suppression>
  <Suppression>
    <DiagnosticId>CP0001</DiagnosticId>
    <Target>T:Umbraco.Cms.Core.Manifest.ManifestContentAppDefinition</Target>
    <Left>lib/net7.0/Umbraco.Core.dll</Left>
    <Right>lib/net7.0/Umbraco.Core.dll</Right>
    <IsBaselineSuppression>true</IsBaselineSuppression>
  </Suppression>
  <Suppression>
    <DiagnosticId>CP0001</DiagnosticId>
    <Target>T:Umbraco.Cms.Core.Manifest.ManifestContentAppFactory</Target>
    <Left>lib/net7.0/Umbraco.Core.dll</Left>
    <Right>lib/net7.0/Umbraco.Core.dll</Right>
    <IsBaselineSuppression>true</IsBaselineSuppression>
  </Suppression>
  <Suppression>
    <DiagnosticId>CP0001</DiagnosticId>
    <Target>T:Umbraco.Cms.Core.Manifest.ManifestDashboard</Target>
    <Left>lib/net7.0/Umbraco.Core.dll</Left>
    <Right>lib/net7.0/Umbraco.Core.dll</Right>
    <IsBaselineSuppression>true</IsBaselineSuppression>
  </Suppression>
  <Suppression>
    <DiagnosticId>CP0001</DiagnosticId>
    <Target>T:Umbraco.Cms.Core.Manifest.ManifestFilterCollection</Target>
    <Left>lib/net7.0/Umbraco.Core.dll</Left>
    <Right>lib/net7.0/Umbraco.Core.dll</Right>
    <IsBaselineSuppression>true</IsBaselineSuppression>
  </Suppression>
  <Suppression>
    <DiagnosticId>CP0001</DiagnosticId>
    <Target>T:Umbraco.Cms.Core.Manifest.ManifestFilterCollectionBuilder</Target>
    <Left>lib/net7.0/Umbraco.Core.dll</Left>
    <Right>lib/net7.0/Umbraco.Core.dll</Right>
    <IsBaselineSuppression>true</IsBaselineSuppression>
  </Suppression>
  <Suppression>
    <DiagnosticId>CP0001</DiagnosticId>
    <Target>T:Umbraco.Cms.Core.Manifest.ManifestSection</Target>
    <Left>lib/net7.0/Umbraco.Core.dll</Left>
    <Right>lib/net7.0/Umbraco.Core.dll</Right>
    <IsBaselineSuppression>true</IsBaselineSuppression>
  </Suppression>
  <Suppression>
    <DiagnosticId>CP0002</DiagnosticId>
    <Target>M:Umbraco.Cms.Core.Configuration.Grid.GridConfig.#ctor(Umbraco.Cms.Core.Cache.AppCaches,Umbraco.Cms.Core.Manifest.IManifestParser,Umbraco.Cms.Core.Serialization.IJsonSerializer,Umbraco.Cms.Core.Hosting.IHostingEnvironment,Microsoft.Extensions.Logging.ILoggerFactory,Umbraco.Cms.Core.IO.IGridEditorsConfigFileProviderFactory)</Target>
    <Left>lib/net7.0/Umbraco.Core.dll</Left>
    <Right>lib/net7.0/Umbraco.Core.dll</Right>
    <IsBaselineSuppression>true</IsBaselineSuppression>
  </Suppression>
  <Suppression>
    <DiagnosticId>CP0002</DiagnosticId>
    <Target>M:Umbraco.Cms.Core.Configuration.Grid.GridConfig.#ctor(Umbraco.Cms.Core.Cache.AppCaches,Umbraco.Cms.Core.Manifest.IManifestParser,Umbraco.Cms.Core.Serialization.IJsonSerializer,Umbraco.Cms.Core.Hosting.IHostingEnvironment,Microsoft.Extensions.Logging.ILoggerFactory)</Target>
    <Left>lib/net7.0/Umbraco.Core.dll</Left>
    <Right>lib/net7.0/Umbraco.Core.dll</Right>
    <IsBaselineSuppression>true</IsBaselineSuppression>
  </Suppression>
  <Suppression>
    <DiagnosticId>CP0002</DiagnosticId>
    <Target>M:Umbraco.Cms.Core.Manifest.PackageManifest.get_AllowPackageTelemetry</Target>
    <Left>lib/net7.0/Umbraco.Core.dll</Left>
    <Right>lib/net7.0/Umbraco.Core.dll</Right>
    <IsBaselineSuppression>true</IsBaselineSuppression>
  </Suppression>
  <Suppression>
    <DiagnosticId>CP0002</DiagnosticId>
    <Target>M:Umbraco.Cms.Core.Manifest.PackageManifest.get_BundleOptions</Target>
    <Left>lib/net7.0/Umbraco.Core.dll</Left>
    <Right>lib/net7.0/Umbraco.Core.dll</Right>
    <IsBaselineSuppression>true</IsBaselineSuppression>
  </Suppression>
  <Suppression>
    <DiagnosticId>CP0002</DiagnosticId>
    <Target>M:Umbraco.Cms.Core.Manifest.PackageManifest.get_ContentApps</Target>
    <Left>lib/net7.0/Umbraco.Core.dll</Left>
    <Right>lib/net7.0/Umbraco.Core.dll</Right>
    <IsBaselineSuppression>true</IsBaselineSuppression>
  </Suppression>
  <Suppression>
    <DiagnosticId>CP0002</DiagnosticId>
    <Target>M:Umbraco.Cms.Core.Manifest.PackageManifest.get_Dashboards</Target>
    <Left>lib/net7.0/Umbraco.Core.dll</Left>
    <Right>lib/net7.0/Umbraco.Core.dll</Right>
    <IsBaselineSuppression>true</IsBaselineSuppression>
  </Suppression>
  <Suppression>
    <DiagnosticId>CP0002</DiagnosticId>
    <Target>M:Umbraco.Cms.Core.Manifest.PackageManifest.get_GridEditors</Target>
    <Left>lib/net7.0/Umbraco.Core.dll</Left>
    <Right>lib/net7.0/Umbraco.Core.dll</Right>
    <IsBaselineSuppression>true</IsBaselineSuppression>
  </Suppression>
  <Suppression>
    <DiagnosticId>CP0002</DiagnosticId>
    <Target>M:Umbraco.Cms.Core.Manifest.PackageManifest.get_PackageName</Target>
    <Left>lib/net7.0/Umbraco.Core.dll</Left>
    <Right>lib/net7.0/Umbraco.Core.dll</Right>
    <IsBaselineSuppression>true</IsBaselineSuppression>
  </Suppression>
  <Suppression>
    <DiagnosticId>CP0002</DiagnosticId>
    <Target>M:Umbraco.Cms.Core.Manifest.PackageManifest.get_PackageView</Target>
    <Left>lib/net7.0/Umbraco.Core.dll</Left>
    <Right>lib/net7.0/Umbraco.Core.dll</Right>
    <IsBaselineSuppression>true</IsBaselineSuppression>
  </Suppression>
  <Suppression>
    <DiagnosticId>CP0002</DiagnosticId>
    <Target>M:Umbraco.Cms.Core.Manifest.PackageManifest.get_ParameterEditors</Target>
    <Left>lib/net7.0/Umbraco.Core.dll</Left>
    <Right>lib/net7.0/Umbraco.Core.dll</Right>
    <IsBaselineSuppression>true</IsBaselineSuppression>
  </Suppression>
  <Suppression>
    <DiagnosticId>CP0002</DiagnosticId>
    <Target>M:Umbraco.Cms.Core.Manifest.PackageManifest.get_PropertyEditors</Target>
    <Left>lib/net7.0/Umbraco.Core.dll</Left>
    <Right>lib/net7.0/Umbraco.Core.dll</Right>
    <IsBaselineSuppression>true</IsBaselineSuppression>
  </Suppression>
  <Suppression>
    <DiagnosticId>CP0002</DiagnosticId>
    <Target>M:Umbraco.Cms.Core.Manifest.PackageManifest.get_Scripts</Target>
    <Left>lib/net7.0/Umbraco.Core.dll</Left>
    <Right>lib/net7.0/Umbraco.Core.dll</Right>
    <IsBaselineSuppression>true</IsBaselineSuppression>
  </Suppression>
  <Suppression>
    <DiagnosticId>CP0002</DiagnosticId>
    <Target>M:Umbraco.Cms.Core.Manifest.PackageManifest.get_Sections</Target>
    <Left>lib/net7.0/Umbraco.Core.dll</Left>
    <Right>lib/net7.0/Umbraco.Core.dll</Right>
    <IsBaselineSuppression>true</IsBaselineSuppression>
  </Suppression>
  <Suppression>
    <DiagnosticId>CP0002</DiagnosticId>
    <Target>M:Umbraco.Cms.Core.Manifest.PackageManifest.get_Source</Target>
    <Left>lib/net7.0/Umbraco.Core.dll</Left>
    <Right>lib/net7.0/Umbraco.Core.dll</Right>
    <IsBaselineSuppression>true</IsBaselineSuppression>
  </Suppression>
  <Suppression>
    <DiagnosticId>CP0002</DiagnosticId>
    <Target>M:Umbraco.Cms.Core.Manifest.PackageManifest.get_Stylesheets</Target>
    <Left>lib/net7.0/Umbraco.Core.dll</Left>
    <Right>lib/net7.0/Umbraco.Core.dll</Right>
    <IsBaselineSuppression>true</IsBaselineSuppression>
  </Suppression>
  <Suppression>
    <DiagnosticId>CP0002</DiagnosticId>
    <Target>M:Umbraco.Cms.Core.Manifest.PackageManifest.set_AllowPackageTelemetry(System.Boolean)</Target>
    <Left>lib/net7.0/Umbraco.Core.dll</Left>
    <Right>lib/net7.0/Umbraco.Core.dll</Right>
    <IsBaselineSuppression>true</IsBaselineSuppression>
  </Suppression>
  <Suppression>
    <DiagnosticId>CP0002</DiagnosticId>
    <Target>M:Umbraco.Cms.Core.Manifest.PackageManifest.set_BundleOptions(Umbraco.Cms.Core.Manifest.BundleOptions)</Target>
    <Left>lib/net7.0/Umbraco.Core.dll</Left>
    <Right>lib/net7.0/Umbraco.Core.dll</Right>
    <IsBaselineSuppression>true</IsBaselineSuppression>
  </Suppression>
  <Suppression>
    <DiagnosticId>CP0002</DiagnosticId>
    <Target>M:Umbraco.Cms.Core.Manifest.PackageManifest.set_ContentApps(Umbraco.Cms.Core.Manifest.ManifestContentAppDefinition[])</Target>
    <Left>lib/net7.0/Umbraco.Core.dll</Left>
    <Right>lib/net7.0/Umbraco.Core.dll</Right>
    <IsBaselineSuppression>true</IsBaselineSuppression>
  </Suppression>
  <Suppression>
    <DiagnosticId>CP0002</DiagnosticId>
    <Target>M:Umbraco.Cms.Core.Manifest.PackageManifest.set_Dashboards(Umbraco.Cms.Core.Manifest.ManifestDashboard[])</Target>
    <Left>lib/net7.0/Umbraco.Core.dll</Left>
    <Right>lib/net7.0/Umbraco.Core.dll</Right>
    <IsBaselineSuppression>true</IsBaselineSuppression>
  </Suppression>
  <Suppression>
    <DiagnosticId>CP0002</DiagnosticId>
    <Target>M:Umbraco.Cms.Core.Manifest.PackageManifest.set_GridEditors(Umbraco.Cms.Core.PropertyEditors.GridEditor[])</Target>
    <Left>lib/net7.0/Umbraco.Core.dll</Left>
    <Right>lib/net7.0/Umbraco.Core.dll</Right>
    <IsBaselineSuppression>true</IsBaselineSuppression>
  </Suppression>
  <Suppression>
    <DiagnosticId>CP0002</DiagnosticId>
    <Target>M:Umbraco.Cms.Core.Manifest.PackageManifest.set_PackageName(System.String)</Target>
    <Left>lib/net7.0/Umbraco.Core.dll</Left>
    <Right>lib/net7.0/Umbraco.Core.dll</Right>
    <IsBaselineSuppression>true</IsBaselineSuppression>
  </Suppression>
  <Suppression>
    <DiagnosticId>CP0002</DiagnosticId>
    <Target>M:Umbraco.Cms.Core.Manifest.PackageManifest.set_PackageView(System.String)</Target>
    <Left>lib/net7.0/Umbraco.Core.dll</Left>
    <Right>lib/net7.0/Umbraco.Core.dll</Right>
    <IsBaselineSuppression>true</IsBaselineSuppression>
  </Suppression>
  <Suppression>
    <DiagnosticId>CP0002</DiagnosticId>
    <Target>M:Umbraco.Cms.Core.Manifest.PackageManifest.set_ParameterEditors(Umbraco.Cms.Core.PropertyEditors.IDataEditor[])</Target>
    <Left>lib/net7.0/Umbraco.Core.dll</Left>
    <Right>lib/net7.0/Umbraco.Core.dll</Right>
    <IsBaselineSuppression>true</IsBaselineSuppression>
  </Suppression>
  <Suppression>
    <DiagnosticId>CP0002</DiagnosticId>
    <Target>M:Umbraco.Cms.Core.Manifest.PackageManifest.set_PropertyEditors(Umbraco.Cms.Core.PropertyEditors.IDataEditor[])</Target>
    <Left>lib/net7.0/Umbraco.Core.dll</Left>
    <Right>lib/net7.0/Umbraco.Core.dll</Right>
    <IsBaselineSuppression>true</IsBaselineSuppression>
  </Suppression>
  <Suppression>
    <DiagnosticId>CP0002</DiagnosticId>
    <Target>M:Umbraco.Cms.Core.Manifest.PackageManifest.set_Scripts(System.String[])</Target>
    <Left>lib/net7.0/Umbraco.Core.dll</Left>
    <Right>lib/net7.0/Umbraco.Core.dll</Right>
    <IsBaselineSuppression>true</IsBaselineSuppression>
  </Suppression>
  <Suppression>
    <DiagnosticId>CP0002</DiagnosticId>
    <Target>M:Umbraco.Cms.Core.Manifest.PackageManifest.set_Sections(Umbraco.Cms.Core.Manifest.ManifestSection[])</Target>
    <Left>lib/net7.0/Umbraco.Core.dll</Left>
    <Right>lib/net7.0/Umbraco.Core.dll</Right>
    <IsBaselineSuppression>true</IsBaselineSuppression>
  </Suppression>
  <Suppression>
    <DiagnosticId>CP0002</DiagnosticId>
    <Target>M:Umbraco.Cms.Core.Manifest.PackageManifest.set_Source(System.String)</Target>
    <Left>lib/net7.0/Umbraco.Core.dll</Left>
    <Right>lib/net7.0/Umbraco.Core.dll</Right>
    <IsBaselineSuppression>true</IsBaselineSuppression>
  </Suppression>
  <Suppression>
    <DiagnosticId>CP0002</DiagnosticId>
    <Target>M:Umbraco.Cms.Core.Manifest.PackageManifest.set_Stylesheets(System.String[])</Target>
    <Left>lib/net7.0/Umbraco.Core.dll</Left>
    <Right>lib/net7.0/Umbraco.Core.dll</Right>
    <IsBaselineSuppression>true</IsBaselineSuppression>
  </Suppression>
  <Suppression>
    <DiagnosticId>CP0002</DiagnosticId>
    <Target>M:Umbraco.Cms.Core.Models.AuditItem.#ctor(System.Int32,Umbraco.Cms.Core.Models.AuditType,System.Int32,System.String,System.String,System.String)</Target>
    <Left>lib/net7.0/Umbraco.Core.dll</Left>
    <Right>lib/net7.0/Umbraco.Core.dll</Right>
    <IsBaselineSuppression>true</IsBaselineSuppression>
  </Suppression>
  <Suppression>
    <DiagnosticId>CP0002</DiagnosticId>
    <Target>M:Umbraco.Cms.Core.Models.Blocks.BlockGridItem.get_ForceLeft</Target>
    <Left>lib/net7.0/Umbraco.Core.dll</Left>
    <Right>lib/net7.0/Umbraco.Core.dll</Right>
    <IsBaselineSuppression>true</IsBaselineSuppression>
  </Suppression>
  <Suppression>
    <DiagnosticId>CP0002</DiagnosticId>
    <Target>M:Umbraco.Cms.Core.Models.Blocks.BlockGridItem.get_ForceRight</Target>
    <Left>lib/net7.0/Umbraco.Core.dll</Left>
    <Right>lib/net7.0/Umbraco.Core.dll</Right>
    <IsBaselineSuppression>true</IsBaselineSuppression>
  </Suppression>
  <Suppression>
    <DiagnosticId>CP0002</DiagnosticId>
    <Target>M:Umbraco.Cms.Core.Models.Blocks.BlockGridItem.set_ForceLeft(System.Boolean)</Target>
    <Left>lib/net7.0/Umbraco.Core.dll</Left>
    <Right>lib/net7.0/Umbraco.Core.dll</Right>
    <IsBaselineSuppression>true</IsBaselineSuppression>
  </Suppression>
  <Suppression>
    <DiagnosticId>CP0002</DiagnosticId>
    <Target>M:Umbraco.Cms.Core.Models.Blocks.BlockGridItem.set_ForceRight(System.Boolean)</Target>
    <Left>lib/net7.0/Umbraco.Core.dll</Left>
    <Right>lib/net7.0/Umbraco.Core.dll</Right>
    <IsBaselineSuppression>true</IsBaselineSuppression>
  </Suppression>
  <Suppression>
    <DiagnosticId>CP0002</DiagnosticId>
    <Target>M:Umbraco.Cms.Core.Models.ContentEditing.ContentPropertyDisplay.get_ConfigNullable</Target>
    <Left>lib/net7.0/Umbraco.Core.dll</Left>
    <Right>lib/net7.0/Umbraco.Core.dll</Right>
    <IsBaselineSuppression>true</IsBaselineSuppression>
  </Suppression>
  <Suppression>
    <DiagnosticId>CP0002</DiagnosticId>
    <Target>M:Umbraco.Cms.Core.Models.ContentEditing.ContentPropertyDisplay.set_ConfigNullable(System.Collections.Generic.IDictionary{System.String,System.Object})</Target>
    <Left>lib/net7.0/Umbraco.Core.dll</Left>
    <Right>lib/net7.0/Umbraco.Core.dll</Right>
    <IsBaselineSuppression>true</IsBaselineSuppression>
  </Suppression>
  <Suppression>
    <DiagnosticId>CP0002</DiagnosticId>
    <Target>M:Umbraco.Cms.Core.Models.ContentEditing.Language.get_FallbackLanguageId</Target>
    <Left>lib/net7.0/Umbraco.Core.dll</Left>
    <Right>lib/net7.0/Umbraco.Core.dll</Right>
    <IsBaselineSuppression>true</IsBaselineSuppression>
  </Suppression>
  <Suppression>
    <DiagnosticId>CP0002</DiagnosticId>
    <Target>M:Umbraco.Cms.Core.Models.ContentEditing.Language.set_FallbackLanguageId(System.Nullable{System.Int32})</Target>
    <Left>lib/net7.0/Umbraco.Core.dll</Left>
    <Right>lib/net7.0/Umbraco.Core.dll</Right>
    <IsBaselineSuppression>true</IsBaselineSuppression>
  </Suppression>
  <Suppression>
    <DiagnosticId>CP0002</DiagnosticId>
    <Target>M:Umbraco.Cms.Core.Models.ContentTypeSort.#ctor(System.Lazy{System.Int32},System.Int32,System.String)</Target>
    <Left>lib/net7.0/Umbraco.Core.dll</Left>
    <Right>lib/net7.0/Umbraco.Core.dll</Right>
    <IsBaselineSuppression>true</IsBaselineSuppression>
  </Suppression>
  <Suppression>
    <DiagnosticId>CP0002</DiagnosticId>
    <Target>M:Umbraco.Cms.Core.Models.DataType.get_Configuration</Target>
    <Left>lib/net7.0/Umbraco.Core.dll</Left>
    <Right>lib/net7.0/Umbraco.Core.dll</Right>
    <IsBaselineSuppression>true</IsBaselineSuppression>
  </Suppression>
  <Suppression>
    <DiagnosticId>CP0002</DiagnosticId>
    <Target>M:Umbraco.Cms.Core.Models.DataType.set_Configuration(System.Object)</Target>
    <Left>lib/net7.0/Umbraco.Core.dll</Left>
    <Right>lib/net7.0/Umbraco.Core.dll</Right>
    <IsBaselineSuppression>true</IsBaselineSuppression>
  </Suppression>
  <Suppression>
    <DiagnosticId>CP0002</DiagnosticId>
    <Target>M:Umbraco.Cms.Core.Models.DataType.SetLazyConfiguration(System.String)</Target>
    <Left>lib/net7.0/Umbraco.Core.dll</Left>
    <Right>lib/net7.0/Umbraco.Core.dll</Right>
    <IsBaselineSuppression>true</IsBaselineSuppression>
  </Suppression>
  <Suppression>
    <DiagnosticId>CP0002</DiagnosticId>
    <Target>M:Umbraco.Cms.Core.Models.DictionaryItem.get_GetLanguage</Target>
    <Left>lib/net7.0/Umbraco.Core.dll</Left>
    <Right>lib/net7.0/Umbraco.Core.dll</Right>
    <IsBaselineSuppression>true</IsBaselineSuppression>
  </Suppression>
  <Suppression>
    <DiagnosticId>CP0002</DiagnosticId>
    <Target>M:Umbraco.Cms.Core.Models.DictionaryItem.set_GetLanguage(System.Func{System.Int32,Umbraco.Cms.Core.Models.ILanguage})</Target>
    <Left>lib/net7.0/Umbraco.Core.dll</Left>
    <Right>lib/net7.0/Umbraco.Core.dll</Right>
    <IsBaselineSuppression>true</IsBaselineSuppression>
  </Suppression>
  <Suppression>
    <DiagnosticId>CP0002</DiagnosticId>
    <Target>M:Umbraco.Cms.Core.Models.DictionaryTranslation.#ctor(System.Int32,System.String,System.Guid)</Target>
    <Left>lib/net7.0/Umbraco.Core.dll</Left>
    <Right>lib/net7.0/Umbraco.Core.dll</Right>
    <IsBaselineSuppression>true</IsBaselineSuppression>
  </Suppression>
  <Suppression>
    <DiagnosticId>CP0002</DiagnosticId>
    <Target>M:Umbraco.Cms.Core.Models.DictionaryTranslation.#ctor(System.Int32,System.String)</Target>
    <Left>lib/net7.0/Umbraco.Core.dll</Left>
    <Right>lib/net7.0/Umbraco.Core.dll</Right>
    <IsBaselineSuppression>true</IsBaselineSuppression>
  </Suppression>
  <Suppression>
    <DiagnosticId>CP0002</DiagnosticId>
    <Target>M:Umbraco.Cms.Core.Models.DictionaryTranslation.get_GetLanguage</Target>
    <Left>lib/net7.0/Umbraco.Core.dll</Left>
    <Right>lib/net7.0/Umbraco.Core.dll</Right>
    <IsBaselineSuppression>true</IsBaselineSuppression>
  </Suppression>
  <Suppression>
    <DiagnosticId>CP0002</DiagnosticId>
    <Target>M:Umbraco.Cms.Core.Models.DictionaryTranslation.get_Language</Target>
    <Left>lib/net7.0/Umbraco.Core.dll</Left>
    <Right>lib/net7.0/Umbraco.Core.dll</Right>
    <IsBaselineSuppression>true</IsBaselineSuppression>
  </Suppression>
  <Suppression>
    <DiagnosticId>CP0002</DiagnosticId>
    <Target>M:Umbraco.Cms.Core.Models.DictionaryTranslation.get_LanguageId</Target>
    <Left>lib/net7.0/Umbraco.Core.dll</Left>
    <Right>lib/net7.0/Umbraco.Core.dll</Right>
    <IsBaselineSuppression>true</IsBaselineSuppression>
  </Suppression>
  <Suppression>
    <DiagnosticId>CP0002</DiagnosticId>
    <Target>M:Umbraco.Cms.Core.Models.DictionaryTranslation.set_GetLanguage(System.Func{System.Int32,Umbraco.Cms.Core.Models.ILanguage})</Target>
    <Left>lib/net7.0/Umbraco.Core.dll</Left>
    <Right>lib/net7.0/Umbraco.Core.dll</Right>
    <IsBaselineSuppression>true</IsBaselineSuppression>
  </Suppression>
  <Suppression>
    <DiagnosticId>CP0002</DiagnosticId>
    <Target>M:Umbraco.Cms.Core.Models.DictionaryTranslation.set_Language(Umbraco.Cms.Core.Models.ILanguage)</Target>
    <Left>lib/net7.0/Umbraco.Core.dll</Left>
    <Right>lib/net7.0/Umbraco.Core.dll</Right>
    <IsBaselineSuppression>true</IsBaselineSuppression>
  </Suppression>
  <Suppression>
    <DiagnosticId>CP0002</DiagnosticId>
    <Target>M:Umbraco.Cms.Core.Models.IDataType.get_Configuration</Target>
    <Left>lib/net7.0/Umbraco.Core.dll</Left>
    <Right>lib/net7.0/Umbraco.Core.dll</Right>
    <IsBaselineSuppression>true</IsBaselineSuppression>
  </Suppression>
  <Suppression>
    <DiagnosticId>CP0002</DiagnosticId>
    <Target>M:Umbraco.Cms.Core.Models.IDataType.set_Configuration(System.Object)</Target>
    <Left>lib/net7.0/Umbraco.Core.dll</Left>
    <Right>lib/net7.0/Umbraco.Core.dll</Right>
    <IsBaselineSuppression>true</IsBaselineSuppression>
  </Suppression>
  <Suppression>
    <DiagnosticId>CP0002</DiagnosticId>
    <Target>M:Umbraco.Cms.Core.Models.IDictionaryTranslation.get_Language</Target>
    <Left>lib/net7.0/Umbraco.Core.dll</Left>
    <Right>lib/net7.0/Umbraco.Core.dll</Right>
    <IsBaselineSuppression>true</IsBaselineSuppression>
  </Suppression>
  <Suppression>
    <DiagnosticId>CP0002</DiagnosticId>
    <Target>M:Umbraco.Cms.Core.Models.IDictionaryTranslation.get_LanguageId</Target>
    <Left>lib/net7.0/Umbraco.Core.dll</Left>
    <Right>lib/net7.0/Umbraco.Core.dll</Right>
    <IsBaselineSuppression>true</IsBaselineSuppression>
  </Suppression>
  <Suppression>
    <DiagnosticId>CP0002</DiagnosticId>
    <Target>M:Umbraco.Cms.Core.Models.IDictionaryTranslation.set_Language(Umbraco.Cms.Core.Models.ILanguage)</Target>
    <Left>lib/net7.0/Umbraco.Core.dll</Left>
    <Right>lib/net7.0/Umbraco.Core.dll</Right>
    <IsBaselineSuppression>true</IsBaselineSuppression>
  </Suppression>
  <Suppression>
    <DiagnosticId>CP0002</DiagnosticId>
    <Target>M:Umbraco.Cms.Core.Models.ILanguage.get_FallbackLanguageId</Target>
    <Left>lib/net7.0/Umbraco.Core.dll</Left>
    <Right>lib/net7.0/Umbraco.Core.dll</Right>
    <IsBaselineSuppression>true</IsBaselineSuppression>
  </Suppression>
  <Suppression>
    <DiagnosticId>CP0002</DiagnosticId>
    <Target>M:Umbraco.Cms.Core.Models.ILanguage.set_FallbackLanguageId(System.Nullable{System.Int32})</Target>
    <Left>lib/net7.0/Umbraco.Core.dll</Left>
    <Right>lib/net7.0/Umbraco.Core.dll</Right>
    <IsBaselineSuppression>true</IsBaselineSuppression>
  </Suppression>
  <Suppression>
    <DiagnosticId>CP0002</DiagnosticId>
    <Target>M:Umbraco.Cms.Core.Models.Language.get_FallbackLanguageId</Target>
    <Left>lib/net7.0/Umbraco.Core.dll</Left>
    <Right>lib/net7.0/Umbraco.Core.dll</Right>
    <IsBaselineSuppression>true</IsBaselineSuppression>
  </Suppression>
  <Suppression>
    <DiagnosticId>CP0002</DiagnosticId>
    <Target>M:Umbraco.Cms.Core.Models.Language.set_FallbackLanguageId(System.Nullable{System.Int32})</Target>
    <Left>lib/net7.0/Umbraco.Core.dll</Left>
    <Right>lib/net7.0/Umbraco.Core.dll</Right>
    <IsBaselineSuppression>true</IsBaselineSuppression>
  </Suppression>
  <Suppression>
    <DiagnosticId>CP0002</DiagnosticId>
    <Target>M:Umbraco.Cms.Core.Models.Mapping.UserMapDefinition.#ctor(Umbraco.Cms.Core.Services.ILocalizedTextService,Umbraco.Cms.Core.Services.IUserService,Umbraco.Cms.Core.Services.IEntityService,Umbraco.Cms.Core.Services.ISectionService,Umbraco.Cms.Core.Cache.AppCaches,Umbraco.Cms.Core.Actions.ActionCollection,Microsoft.Extensions.Options.IOptions{Umbraco.Cms.Core.Configuration.Models.GlobalSettings},Umbraco.Cms.Core.IO.MediaFileManager,Umbraco.Cms.Core.Strings.IShortStringHelper,Umbraco.Cms.Core.Media.IImageUrlGenerator)</Target>
    <Left>lib/net7.0/Umbraco.Core.dll</Left>
    <Right>lib/net7.0/Umbraco.Core.dll</Right>
    <IsBaselineSuppression>true</IsBaselineSuppression>
  </Suppression>
  <Suppression>
    <DiagnosticId>CP0002</DiagnosticId>
    <Target>M:Umbraco.Cms.Core.Models.Membership.ReadOnlyUserGroup.#ctor(System.Int32,System.String,System.String,System.Nullable{System.Int32},System.Nullable{System.Int32},System.String,System.Collections.Generic.IEnumerable{System.Int32},System.Collections.Generic.IEnumerable{System.String},System.Collections.Generic.IEnumerable{System.String},System.Boolean)</Target>
    <Left>lib/net7.0/Umbraco.Core.dll</Left>
    <Right>lib/net7.0/Umbraco.Core.dll</Right>
    <IsBaselineSuppression>true</IsBaselineSuppression>
  </Suppression>
  <Suppression>
    <DiagnosticId>CP0002</DiagnosticId>
    <Target>M:Umbraco.Cms.Core.Models.Membership.ReadOnlyUserGroup.#ctor(System.Int32,System.String,System.String,System.Nullable{System.Int32},System.Nullable{System.Int32},System.String,System.Collections.Generic.IEnumerable{System.String},System.Collections.Generic.IEnumerable{System.String})</Target>
    <Left>lib/net7.0/Umbraco.Core.dll</Left>
    <Right>lib/net7.0/Umbraco.Core.dll</Right>
    <IsBaselineSuppression>true</IsBaselineSuppression>
  </Suppression>
  <Suppression>
    <DiagnosticId>CP0002</DiagnosticId>
    <Target>M:Umbraco.Cms.Core.Models.PasswordChangedModel.get_ChangeError</Target>
    <Left>lib/net7.0/Umbraco.Core.dll</Left>
    <Right>lib/net7.0/Umbraco.Core.dll</Right>
    <IsBaselineSuppression>true</IsBaselineSuppression>
  </Suppression>
  <Suppression>
    <DiagnosticId>CP0002</DiagnosticId>
    <Target>M:Umbraco.Cms.Core.Models.PasswordChangedModel.set_ChangeError(System.ComponentModel.DataAnnotations.ValidationResult)</Target>
    <Left>lib/net7.0/Umbraco.Core.dll</Left>
    <Right>lib/net7.0/Umbraco.Core.dll</Right>
    <IsBaselineSuppression>true</IsBaselineSuppression>
  </Suppression>
  <Suppression>
    <DiagnosticId>CP0002</DiagnosticId>
    <Target>M:Umbraco.Cms.Core.Models.PublishedContent.PublishedDataType.get_Configuration</Target>
    <Left>lib/net7.0/Umbraco.Core.dll</Left>
    <Right>lib/net7.0/Umbraco.Core.dll</Right>
    <IsBaselineSuppression>true</IsBaselineSuppression>
  </Suppression>
  <Suppression>
    <DiagnosticId>CP0002</DiagnosticId>
    <Target>M:Umbraco.Cms.Core.Models.RelationType.#ctor(System.String,System.String,System.Boolean,System.Nullable{System.Guid},System.Nullable{System.Guid},System.Boolean)</Target>
    <Left>lib/net7.0/Umbraco.Core.dll</Left>
    <Right>lib/net7.0/Umbraco.Core.dll</Right>
    <IsBaselineSuppression>true</IsBaselineSuppression>
  </Suppression>
  <Suppression>
    <DiagnosticId>CP0002</DiagnosticId>
    <Target>M:Umbraco.Cms.Core.Notifications.ContentMovedToRecycleBinNotification.#ctor(System.Collections.Generic.IEnumerable{Umbraco.Cms.Core.Events.MoveEventInfo{Umbraco.Cms.Core.Models.IContent}},Umbraco.Cms.Core.Events.EventMessages)</Target>
    <Left>lib/net7.0/Umbraco.Core.dll</Left>
    <Right>lib/net7.0/Umbraco.Core.dll</Right>
    <IsBaselineSuppression>true</IsBaselineSuppression>
  </Suppression>
  <Suppression>
    <DiagnosticId>CP0002</DiagnosticId>
    <Target>M:Umbraco.Cms.Core.Notifications.ContentMovedToRecycleBinNotification.#ctor(Umbraco.Cms.Core.Events.MoveEventInfo{Umbraco.Cms.Core.Models.IContent},Umbraco.Cms.Core.Events.EventMessages)</Target>
    <Left>lib/net7.0/Umbraco.Core.dll</Left>
    <Right>lib/net7.0/Umbraco.Core.dll</Right>
    <IsBaselineSuppression>true</IsBaselineSuppression>
  </Suppression>
  <Suppression>
    <DiagnosticId>CP0002</DiagnosticId>
    <Target>M:Umbraco.Cms.Core.Notifications.ContentMovingToRecycleBinNotification.#ctor(System.Collections.Generic.IEnumerable{Umbraco.Cms.Core.Events.MoveEventInfo{Umbraco.Cms.Core.Models.IContent}},Umbraco.Cms.Core.Events.EventMessages)</Target>
    <Left>lib/net7.0/Umbraco.Core.dll</Left>
    <Right>lib/net7.0/Umbraco.Core.dll</Right>
    <IsBaselineSuppression>true</IsBaselineSuppression>
  </Suppression>
  <Suppression>
    <DiagnosticId>CP0002</DiagnosticId>
    <Target>M:Umbraco.Cms.Core.Notifications.ContentMovingToRecycleBinNotification.#ctor(Umbraco.Cms.Core.Events.MoveEventInfo{Umbraco.Cms.Core.Models.IContent},Umbraco.Cms.Core.Events.EventMessages)</Target>
    <Left>lib/net7.0/Umbraco.Core.dll</Left>
    <Right>lib/net7.0/Umbraco.Core.dll</Right>
    <IsBaselineSuppression>true</IsBaselineSuppression>
  </Suppression>
  <Suppression>
    <DiagnosticId>CP0002</DiagnosticId>
    <Target>M:Umbraco.Cms.Core.Notifications.MediaMovedToRecycleBinNotification.#ctor(System.Collections.Generic.IEnumerable{Umbraco.Cms.Core.Events.MoveEventInfo{Umbraco.Cms.Core.Models.IMedia}},Umbraco.Cms.Core.Events.EventMessages)</Target>
    <Left>lib/net7.0/Umbraco.Core.dll</Left>
    <Right>lib/net7.0/Umbraco.Core.dll</Right>
    <IsBaselineSuppression>true</IsBaselineSuppression>
  </Suppression>
  <Suppression>
    <DiagnosticId>CP0002</DiagnosticId>
    <Target>M:Umbraco.Cms.Core.Notifications.MediaMovedToRecycleBinNotification.#ctor(Umbraco.Cms.Core.Events.MoveEventInfo{Umbraco.Cms.Core.Models.IMedia},Umbraco.Cms.Core.Events.EventMessages)</Target>
    <Left>lib/net7.0/Umbraco.Core.dll</Left>
    <Right>lib/net7.0/Umbraco.Core.dll</Right>
    <IsBaselineSuppression>true</IsBaselineSuppression>
  </Suppression>
  <Suppression>
    <DiagnosticId>CP0002</DiagnosticId>
    <Target>M:Umbraco.Cms.Core.Notifications.MediaMovingToRecycleBinNotification.#ctor(System.Collections.Generic.IEnumerable{Umbraco.Cms.Core.Events.MoveEventInfo{Umbraco.Cms.Core.Models.IMedia}},Umbraco.Cms.Core.Events.EventMessages)</Target>
    <Left>lib/net7.0/Umbraco.Core.dll</Left>
    <Right>lib/net7.0/Umbraco.Core.dll</Right>
    <IsBaselineSuppression>true</IsBaselineSuppression>
  </Suppression>
  <Suppression>
    <DiagnosticId>CP0002</DiagnosticId>
    <Target>M:Umbraco.Cms.Core.Notifications.MediaMovingToRecycleBinNotification.#ctor(Umbraco.Cms.Core.Events.MoveEventInfo{Umbraco.Cms.Core.Models.IMedia},Umbraco.Cms.Core.Events.EventMessages)</Target>
    <Left>lib/net7.0/Umbraco.Core.dll</Left>
    <Right>lib/net7.0/Umbraco.Core.dll</Right>
    <IsBaselineSuppression>true</IsBaselineSuppression>
  </Suppression>
  <Suppression>
    <DiagnosticId>CP0002</DiagnosticId>
    <Target>M:Umbraco.Cms.Core.Notifications.MovedToRecycleBinNotification`1.#ctor(System.Collections.Generic.IEnumerable{Umbraco.Cms.Core.Events.MoveEventInfo{`0}},Umbraco.Cms.Core.Events.EventMessages)</Target>
    <Left>lib/net7.0/Umbraco.Core.dll</Left>
    <Right>lib/net7.0/Umbraco.Core.dll</Right>
    <IsBaselineSuppression>true</IsBaselineSuppression>
  </Suppression>
  <Suppression>
    <DiagnosticId>CP0002</DiagnosticId>
    <Target>M:Umbraco.Cms.Core.Notifications.MovedToRecycleBinNotification`1.#ctor(Umbraco.Cms.Core.Events.MoveEventInfo{`0},Umbraco.Cms.Core.Events.EventMessages)</Target>
    <Left>lib/net7.0/Umbraco.Core.dll</Left>
    <Right>lib/net7.0/Umbraco.Core.dll</Right>
    <IsBaselineSuppression>true</IsBaselineSuppression>
  </Suppression>
  <Suppression>
    <DiagnosticId>CP0002</DiagnosticId>
    <Target>M:Umbraco.Cms.Core.Notifications.MovingToRecycleBinNotification`1.#ctor(System.Collections.Generic.IEnumerable{Umbraco.Cms.Core.Events.MoveEventInfo{`0}},Umbraco.Cms.Core.Events.EventMessages)</Target>
    <Left>lib/net7.0/Umbraco.Core.dll</Left>
    <Right>lib/net7.0/Umbraco.Core.dll</Right>
    <IsBaselineSuppression>true</IsBaselineSuppression>
  </Suppression>
  <Suppression>
    <DiagnosticId>CP0002</DiagnosticId>
    <Target>M:Umbraco.Cms.Core.Notifications.MovingToRecycleBinNotification`1.#ctor(Umbraco.Cms.Core.Events.MoveEventInfo{`0},Umbraco.Cms.Core.Events.EventMessages)</Target>
    <Left>lib/net7.0/Umbraco.Core.dll</Left>
    <Right>lib/net7.0/Umbraco.Core.dll</Right>
    <IsBaselineSuppression>true</IsBaselineSuppression>
  </Suppression>
  <Suppression>
    <DiagnosticId>CP0002</DiagnosticId>
    <Target>M:Umbraco.Cms.Core.PropertyEditors.ConfigurationEditor.FromConfigurationEditor(System.Collections.Generic.IDictionary{System.String,System.Object},System.Object)</Target>
    <Left>lib/net7.0/Umbraco.Core.dll</Left>
    <Right>lib/net7.0/Umbraco.Core.dll</Right>
    <IsBaselineSuppression>true</IsBaselineSuppression>
  </Suppression>
  <Suppression>
    <DiagnosticId>CP0002</DiagnosticId>
    <Target>M:Umbraco.Cms.Core.PropertyEditors.ConfigurationEditor.get_DefaultConfigurationObject</Target>
    <Left>lib/net7.0/Umbraco.Core.dll</Left>
    <Right>lib/net7.0/Umbraco.Core.dll</Right>
    <IsBaselineSuppression>true</IsBaselineSuppression>
  </Suppression>
  <Suppression>
    <DiagnosticId>CP0002</DiagnosticId>
    <Target>M:Umbraco.Cms.Core.PropertyEditors.ConfigurationEditor.IsConfiguration(System.Object)</Target>
    <Left>lib/net7.0/Umbraco.Core.dll</Left>
    <Right>lib/net7.0/Umbraco.Core.dll</Right>
    <IsBaselineSuppression>true</IsBaselineSuppression>
  </Suppression>
  <Suppression>
    <DiagnosticId>CP0002</DiagnosticId>
    <Target>M:Umbraco.Cms.Core.PropertyEditors.ConfigurationEditor.ToConfigurationEditor(System.Object)</Target>
    <Left>lib/net7.0/Umbraco.Core.dll</Left>
    <Right>lib/net7.0/Umbraco.Core.dll</Right>
    <IsBaselineSuppression>true</IsBaselineSuppression>
  </Suppression>
  <Suppression>
    <DiagnosticId>CP0002</DiagnosticId>
    <Target>M:Umbraco.Cms.Core.PropertyEditors.ConfigurationEditor.ToDatabase(System.Object,Umbraco.Cms.Core.Serialization.IConfigurationEditorJsonSerializer)</Target>
    <Left>lib/net7.0/Umbraco.Core.dll</Left>
    <Right>lib/net7.0/Umbraco.Core.dll</Right>
    <IsBaselineSuppression>true</IsBaselineSuppression>
  </Suppression>
  <Suppression>
    <DiagnosticId>CP0002</DiagnosticId>
    <Target>M:Umbraco.Cms.Core.PropertyEditors.ConfigurationEditor.ToValueEditor(System.Object)</Target>
    <Left>lib/net7.0/Umbraco.Core.dll</Left>
    <Right>lib/net7.0/Umbraco.Core.dll</Right>
    <IsBaselineSuppression>true</IsBaselineSuppression>
  </Suppression>
  <Suppression>
    <DiagnosticId>CP0002</DiagnosticId>
    <Target>M:Umbraco.Cms.Core.PropertyEditors.ConfigurationEditor`1.FromConfigurationEditor(System.Collections.Generic.IDictionary{System.String,System.Object},`0)</Target>
    <Left>lib/net7.0/Umbraco.Core.dll</Left>
    <Right>lib/net7.0/Umbraco.Core.dll</Right>
    <IsBaselineSuppression>true</IsBaselineSuppression>
  </Suppression>
  <Suppression>
    <DiagnosticId>CP0002</DiagnosticId>
    <Target>M:Umbraco.Cms.Core.PropertyEditors.ConfigurationEditor`1.ToConfigurationEditor(`0)</Target>
    <Left>lib/net7.0/Umbraco.Core.dll</Left>
    <Right>lib/net7.0/Umbraco.Core.dll</Right>
    <IsBaselineSuppression>true</IsBaselineSuppression>
  </Suppression>
  <Suppression>
    <DiagnosticId>CP0002</DiagnosticId>
    <Target>M:Umbraco.Cms.Core.PropertyEditors.DataValueEditor.get_Configuration</Target>
    <Left>lib/net7.0/Umbraco.Core.dll</Left>
    <Right>lib/net7.0/Umbraco.Core.dll</Right>
    <IsBaselineSuppression>true</IsBaselineSuppression>
  </Suppression>
  <Suppression>
    <DiagnosticId>CP0002</DiagnosticId>
    <Target>M:Umbraco.Cms.Core.PropertyEditors.DataValueEditor.set_Configuration(System.Object)</Target>
    <Left>lib/net7.0/Umbraco.Core.dll</Left>
    <Right>lib/net7.0/Umbraco.Core.dll</Right>
    <IsBaselineSuppression>true</IsBaselineSuppression>
  </Suppression>
  <Suppression>
    <DiagnosticId>CP0002</DiagnosticId>
    <Target>M:Umbraco.Cms.Core.PropertyEditors.IConfigurationEditor.FromConfigurationEditor(System.Collections.Generic.IDictionary{System.String,System.Object},System.Object)</Target>
    <Left>lib/net7.0/Umbraco.Core.dll</Left>
    <Right>lib/net7.0/Umbraco.Core.dll</Right>
    <IsBaselineSuppression>true</IsBaselineSuppression>
  </Suppression>
  <Suppression>
    <DiagnosticId>CP0002</DiagnosticId>
    <Target>M:Umbraco.Cms.Core.PropertyEditors.IConfigurationEditor.get_DefaultConfigurationObject</Target>
    <Left>lib/net7.0/Umbraco.Core.dll</Left>
    <Right>lib/net7.0/Umbraco.Core.dll</Right>
    <IsBaselineSuppression>true</IsBaselineSuppression>
  </Suppression>
  <Suppression>
    <DiagnosticId>CP0002</DiagnosticId>
    <Target>M:Umbraco.Cms.Core.PropertyEditors.IConfigurationEditor.IsConfiguration(System.Object)</Target>
    <Left>lib/net7.0/Umbraco.Core.dll</Left>
    <Right>lib/net7.0/Umbraco.Core.dll</Right>
    <IsBaselineSuppression>true</IsBaselineSuppression>
  </Suppression>
  <Suppression>
    <DiagnosticId>CP0002</DiagnosticId>
    <Target>M:Umbraco.Cms.Core.PropertyEditors.IConfigurationEditor.ToConfigurationEditor(System.Object)</Target>
    <Left>lib/net7.0/Umbraco.Core.dll</Left>
    <Right>lib/net7.0/Umbraco.Core.dll</Right>
    <IsBaselineSuppression>true</IsBaselineSuppression>
  </Suppression>
  <Suppression>
    <DiagnosticId>CP0002</DiagnosticId>
    <Target>M:Umbraco.Cms.Core.PropertyEditors.IConfigurationEditor.ToConfigurationEditorNullable(System.Object)</Target>
    <Left>lib/net7.0/Umbraco.Core.dll</Left>
    <Right>lib/net7.0/Umbraco.Core.dll</Right>
    <IsBaselineSuppression>true</IsBaselineSuppression>
  </Suppression>
  <Suppression>
    <DiagnosticId>CP0002</DiagnosticId>
    <Target>M:Umbraco.Cms.Core.PropertyEditors.IConfigurationEditor.ToValueEditor(System.Object)</Target>
    <Left>lib/net7.0/Umbraco.Core.dll</Left>
    <Right>lib/net7.0/Umbraco.Core.dll</Right>
    <IsBaselineSuppression>true</IsBaselineSuppression>
  </Suppression>
  <Suppression>
    <DiagnosticId>CP0002</DiagnosticId>
    <Target>M:Umbraco.Cms.Core.PropertyEditors.MultipleTextStringConfiguration.get_Maximum</Target>
    <Left>lib/net7.0/Umbraco.Core.dll</Left>
    <Right>lib/net7.0/Umbraco.Core.dll</Right>
    <IsBaselineSuppression>true</IsBaselineSuppression>
  </Suppression>
  <Suppression>
    <DiagnosticId>CP0002</DiagnosticId>
    <Target>M:Umbraco.Cms.Core.PropertyEditors.MultipleTextStringConfiguration.get_Minimum</Target>
    <Left>lib/net7.0/Umbraco.Core.dll</Left>
    <Right>lib/net7.0/Umbraco.Core.dll</Right>
    <IsBaselineSuppression>true</IsBaselineSuppression>
  </Suppression>
  <Suppression>
    <DiagnosticId>CP0002</DiagnosticId>
    <Target>M:Umbraco.Cms.Core.PropertyEditors.MultipleTextStringConfiguration.set_Maximum(System.Int32)</Target>
    <Left>lib/net7.0/Umbraco.Core.dll</Left>
    <Right>lib/net7.0/Umbraco.Core.dll</Right>
    <IsBaselineSuppression>true</IsBaselineSuppression>
  </Suppression>
  <Suppression>
    <DiagnosticId>CP0002</DiagnosticId>
    <Target>M:Umbraco.Cms.Core.PropertyEditors.MultipleTextStringConfiguration.set_Minimum(System.Int32)</Target>
    <Left>lib/net7.0/Umbraco.Core.dll</Left>
    <Right>lib/net7.0/Umbraco.Core.dll</Right>
    <IsBaselineSuppression>true</IsBaselineSuppression>
  </Suppression>
  <Suppression>
    <DiagnosticId>CP0002</DiagnosticId>
    <Target>M:Umbraco.Cms.Core.PropertyEditors.ParameterEditorCollection.#ctor(Umbraco.Cms.Core.PropertyEditors.DataEditorCollection,Umbraco.Cms.Core.Manifest.IManifestParser)</Target>
    <Left>lib/net7.0/Umbraco.Core.dll</Left>
    <Right>lib/net7.0/Umbraco.Core.dll</Right>
    <IsBaselineSuppression>true</IsBaselineSuppression>
  </Suppression>
  <Suppression>
    <DiagnosticId>CP0002</DiagnosticId>
    <Target>M:Umbraco.Cms.Core.PropertyEditors.PropertyEditorCollection.#ctor(Umbraco.Cms.Core.PropertyEditors.DataEditorCollection,Umbraco.Cms.Core.Manifest.IManifestParser)</Target>
    <Left>lib/net7.0/Umbraco.Core.dll</Left>
    <Right>lib/net7.0/Umbraco.Core.dll</Right>
    <IsBaselineSuppression>true</IsBaselineSuppression>
  </Suppression>
  <Suppression>
    <DiagnosticId>CP0002</DiagnosticId>
    <Target>M:Umbraco.Cms.Core.Services.Implement.AuditService.#ctor(Umbraco.Cms.Core.Scoping.ICoreScopeProvider,Microsoft.Extensions.Logging.ILoggerFactory,Umbraco.Cms.Core.Events.IEventMessagesFactory,Umbraco.Cms.Core.Persistence.Repositories.IAuditRepository,Umbraco.Cms.Core.Persistence.Repositories.IAuditEntryRepository)</Target>
    <Left>lib/net7.0/Umbraco.Core.dll</Left>
    <Right>lib/net7.0/Umbraco.Core.dll</Right>
    <IsBaselineSuppression>true</IsBaselineSuppression>
  </Suppression>
  <Suppression>
    <DiagnosticId>CP0002</DiagnosticId>
    <Target>M:Umbraco.Cms.Core.Services.Implement.DataTypeService.#ctor(Umbraco.Cms.Core.PropertyEditors.IDataValueEditorFactory,Umbraco.Cms.Core.Scoping.ICoreScopeProvider,Microsoft.Extensions.Logging.ILoggerFactory,Umbraco.Cms.Core.Events.IEventMessagesFactory,Umbraco.Cms.Core.Persistence.Repositories.IDataTypeRepository,Umbraco.Cms.Core.Persistence.Repositories.IDataTypeContainerRepository,Umbraco.Cms.Core.Persistence.Repositories.IAuditRepository,Umbraco.Cms.Core.Persistence.Repositories.IEntityRepository,Umbraco.Cms.Core.Persistence.Repositories.IContentTypeRepository,Umbraco.Cms.Core.IO.IIOHelper,Umbraco.Cms.Core.Services.ILocalizedTextService,Umbraco.Cms.Core.Services.ILocalizationService,Umbraco.Cms.Core.Strings.IShortStringHelper,Umbraco.Cms.Core.Serialization.IJsonSerializer)</Target>
    <Left>lib/net7.0/Umbraco.Core.dll</Left>
    <Right>lib/net7.0/Umbraco.Core.dll</Right>
    <IsBaselineSuppression>true</IsBaselineSuppression>
  </Suppression>
  <Suppression>
    <DiagnosticId>CP0002</DiagnosticId>
    <Target>M:Umbraco.Extensions.DictionaryItemExtensions.GetDefaultValue(Umbraco.Cms.Core.Models.IDictionaryItem)</Target>
    <Left>lib/net7.0/Umbraco.Core.dll</Left>
    <Right>lib/net7.0/Umbraco.Core.dll</Right>
    <IsBaselineSuppression>true</IsBaselineSuppression>
  </Suppression>
  <Suppression>
    <DiagnosticId>CP0002</DiagnosticId>
    <Target>M:Umbraco.Extensions.DictionaryItemExtensions.GetTranslatedValue(Umbraco.Cms.Core.Models.IDictionaryItem,System.Int32)</Target>
    <Left>lib/net7.0/Umbraco.Core.dll</Left>
    <Right>lib/net7.0/Umbraco.Core.dll</Right>
    <IsBaselineSuppression>true</IsBaselineSuppression>
  </Suppression>
  <Suppression>
    <DiagnosticId>CP0005</DiagnosticId>
    <Target>M:Umbraco.Cms.Core.Models.PublishedContent.PublishedPropertyBase.GetDeliveryApiValue(System.Boolean,System.String,System.String)</Target>
    <Left>lib/net7.0/Umbraco.Core.dll</Left>
    <Right>lib/net7.0/Umbraco.Core.dll</Right>
    <IsBaselineSuppression>true</IsBaselineSuppression>
  </Suppression>
  <Suppression>
    <DiagnosticId>CP0006</DiagnosticId>
    <Target>M:Umbraco.Cms.Core.Deploy.IDataTypeConfigurationConnector.FromArtifact(Umbraco.Cms.Core.Models.IDataType,System.String,Umbraco.Cms.Core.Deploy.IContextCache)</Target>
    <Left>lib/net7.0/Umbraco.Core.dll</Left>
    <Right>lib/net7.0/Umbraco.Core.dll</Right>
    <IsBaselineSuppression>true</IsBaselineSuppression>
  </Suppression>
  <Suppression>
    <DiagnosticId>CP0006</DiagnosticId>
    <Target>M:Umbraco.Cms.Core.Deploy.IDataTypeConfigurationConnector.ToArtifact(Umbraco.Cms.Core.Models.IDataType,System.Collections.Generic.ICollection{Umbraco.Cms.Core.Deploy.ArtifactDependency},Umbraco.Cms.Core.Deploy.IContextCache)</Target>
    <Left>lib/net7.0/Umbraco.Core.dll</Left>
    <Right>lib/net7.0/Umbraco.Core.dll</Right>
    <IsBaselineSuppression>true</IsBaselineSuppression>
  </Suppression>
  <Suppression>
    <DiagnosticId>CP0006</DiagnosticId>
    <Target>M:Umbraco.Cms.Core.Deploy.IServiceConnector.GetArtifact(System.Object,Umbraco.Cms.Core.Deploy.IContextCache)</Target>
    <Left>lib/net7.0/Umbraco.Core.dll</Left>
    <Right>lib/net7.0/Umbraco.Core.dll</Right>
    <IsBaselineSuppression>true</IsBaselineSuppression>
  </Suppression>
  <Suppression>
    <DiagnosticId>CP0006</DiagnosticId>
    <Target>M:Umbraco.Cms.Core.Deploy.IServiceConnector.GetArtifact(Umbraco.Cms.Core.Udi,Umbraco.Cms.Core.Deploy.IContextCache)</Target>
    <Left>lib/net7.0/Umbraco.Core.dll</Left>
    <Right>lib/net7.0/Umbraco.Core.dll</Right>
    <IsBaselineSuppression>true</IsBaselineSuppression>
  </Suppression>
  <Suppression>
    <DiagnosticId>CP0006</DiagnosticId>
    <Target>M:Umbraco.Cms.Core.Deploy.IValueConnector.FromArtifact(System.String,Umbraco.Cms.Core.Models.IPropertyType,System.Object,Umbraco.Cms.Core.Deploy.IContextCache)</Target>
    <Left>lib/net7.0/Umbraco.Core.dll</Left>
    <Right>lib/net7.0/Umbraco.Core.dll</Right>
    <IsBaselineSuppression>true</IsBaselineSuppression>
  </Suppression>
  <Suppression>
    <DiagnosticId>CP0006</DiagnosticId>
    <Target>M:Umbraco.Cms.Core.Deploy.IValueConnector.ToArtifact(System.Object,Umbraco.Cms.Core.Models.IPropertyType,System.Collections.Generic.ICollection{Umbraco.Cms.Core.Deploy.ArtifactDependency},Umbraco.Cms.Core.Deploy.IContextCache)</Target>
    <Left>lib/net7.0/Umbraco.Core.dll</Left>
    <Right>lib/net7.0/Umbraco.Core.dll</Right>
    <IsBaselineSuppression>true</IsBaselineSuppression>
  </Suppression>
  <Suppression>
    <DiagnosticId>CP0006</DiagnosticId>
    <Target>M:Umbraco.Cms.Core.Models.IContentBase.RemoveValue(System.String)</Target>
    <Left>lib/net7.0/Umbraco.Core.dll</Left>
    <Right>lib/net7.0/Umbraco.Core.dll</Right>
    <IsBaselineSuppression>true</IsBaselineSuppression>
  </Suppression>
  <Suppression>
    <DiagnosticId>CP0006</DiagnosticId>
    <Target>M:Umbraco.Cms.Core.Models.PublishedContent.IPublishedProperty.GetDeliveryApiValue(System.Boolean,System.String,System.String)</Target>
    <Left>lib/net7.0/Umbraco.Core.dll</Left>
    <Right>lib/net7.0/Umbraco.Core.dll</Right>
    <IsBaselineSuppression>true</IsBaselineSuppression>
  </Suppression>
  <Suppression>
    <DiagnosticId>CP0006</DiagnosticId>
    <Target>M:Umbraco.Cms.Core.Models.PublishedContent.IPublishedPropertyType.ConvertInterToDeliveryApiObject(Umbraco.Cms.Core.Models.PublishedContent.IPublishedElement,Umbraco.Cms.Core.PropertyEditors.PropertyCacheLevel,System.Object,System.Boolean)</Target>
    <Left>lib/net7.0/Umbraco.Core.dll</Left>
    <Right>lib/net7.0/Umbraco.Core.dll</Right>
    <IsBaselineSuppression>true</IsBaselineSuppression>
  </Suppression>
  <Suppression>
    <DiagnosticId>CP0006</DiagnosticId>
    <Target>M:Umbraco.Cms.Core.Packaging.IPackageDefinitionRepository.GetByKey(System.Guid)</Target>
    <Left>lib/net7.0/Umbraco.Core.dll</Left>
    <Right>lib/net7.0/Umbraco.Core.dll</Right>
    <IsBaselineSuppression>true</IsBaselineSuppression>
  </Suppression>
  <Suppression>
    <DiagnosticId>CP0006</DiagnosticId>
    <Target>M:Umbraco.Cms.Core.Persistence.Repositories.IDataTypeContainerRepository.HasDuplicateName(System.Guid,System.String)</Target>
    <Left>lib/net7.0/Umbraco.Core.dll</Left>
    <Right>lib/net7.0/Umbraco.Core.dll</Right>
    <IsBaselineSuppression>true</IsBaselineSuppression>
  </Suppression>
  <Suppression>
    <DiagnosticId>CP0006</DiagnosticId>
    <Target>M:Umbraco.Cms.Core.Persistence.Repositories.IDataTypeContainerRepository.HasDuplicateName(System.Int32,System.String)</Target>
    <Left>lib/net7.0/Umbraco.Core.dll</Left>
    <Right>lib/net7.0/Umbraco.Core.dll</Right>
    <IsBaselineSuppression>true</IsBaselineSuppression>
  </Suppression>
  <Suppression>
    <DiagnosticId>CP0006</DiagnosticId>
    <Target>M:Umbraco.Cms.Core.Persistence.Repositories.IDataTypeRepository.Get(System.Guid)</Target>
    <Left>lib/net7.0/Umbraco.Core.dll</Left>
    <Right>lib/net7.0/Umbraco.Core.dll</Right>
    <IsBaselineSuppression>true</IsBaselineSuppression>
  </Suppression>
  <Suppression>
    <DiagnosticId>CP0006</DiagnosticId>
    <Target>M:Umbraco.Cms.Core.Persistence.Repositories.IDataTypeUsageRepository.HasSavedValuesAsync(System.Guid)</Target>
    <Left>lib/net7.0/Umbraco.Core.dll</Left>
    <Right>lib/net7.0/Umbraco.Core.dll</Right>
    <IsBaselineSuppression>true</IsBaselineSuppression>
  </Suppression>
  <Suppression>
    <DiagnosticId>CP0006</DiagnosticId>
    <Target>M:Umbraco.Cms.Core.Persistence.Repositories.IFileWithFoldersRepository.FolderExists(System.String)</Target>
    <Left>lib/net7.0/Umbraco.Core.dll</Left>
    <Right>lib/net7.0/Umbraco.Core.dll</Right>
    <IsBaselineSuppression>true</IsBaselineSuppression>
  </Suppression>
  <Suppression>
    <DiagnosticId>CP0006</DiagnosticId>
    <Target>M:Umbraco.Cms.Core.Persistence.Repositories.IFileWithFoldersRepository.FolderHasContent(System.String)</Target>
    <Left>lib/net7.0/Umbraco.Core.dll</Left>
    <Right>lib/net7.0/Umbraco.Core.dll</Right>
    <IsBaselineSuppression>true</IsBaselineSuppression>
  </Suppression>
  <Suppression>
    <DiagnosticId>CP0006</DiagnosticId>
    <Target>M:Umbraco.Cms.Core.Persistence.Repositories.IPropertyTypeUsageRepository.ContentTypeExistAsync(System.Guid)</Target>
    <Left>lib/net7.0/Umbraco.Core.dll</Left>
    <Right>lib/net7.0/Umbraco.Core.dll</Right>
    <IsBaselineSuppression>true</IsBaselineSuppression>
  </Suppression>
  <Suppression>
    <DiagnosticId>CP0006</DiagnosticId>
    <Target>M:Umbraco.Cms.Core.Persistence.Repositories.IPropertyTypeUsageRepository.HasSavedPropertyValuesAsync(System.Guid,System.String)</Target>
    <Left>lib/net7.0/Umbraco.Core.dll</Left>
    <Right>lib/net7.0/Umbraco.Core.dll</Right>
    <IsBaselineSuppression>true</IsBaselineSuppression>
  </Suppression>
  <Suppression>
    <DiagnosticId>CP0006</DiagnosticId>
    <Target>M:Umbraco.Cms.Core.Persistence.Repositories.ITrackedReferencesRepository.GetPagedDescendantsInReferences(System.Guid,System.Int64,System.Int64,System.Boolean,System.Int64@)</Target>
    <Left>lib/net7.0/Umbraco.Core.dll</Left>
    <Right>lib/net7.0/Umbraco.Core.dll</Right>
    <IsBaselineSuppression>true</IsBaselineSuppression>
  </Suppression>
  <Suppression>
    <DiagnosticId>CP0006</DiagnosticId>
    <Target>M:Umbraco.Cms.Core.Persistence.Repositories.ITrackedReferencesRepository.GetPagedItemsWithRelations(System.Collections.Generic.ISet{System.Guid},System.Int64,System.Int64,System.Boolean,System.Int64@)</Target>
    <Left>lib/net7.0/Umbraco.Core.dll</Left>
    <Right>lib/net7.0/Umbraco.Core.dll</Right>
    <IsBaselineSuppression>true</IsBaselineSuppression>
  </Suppression>
  <Suppression>
    <DiagnosticId>CP0006</DiagnosticId>
    <Target>M:Umbraco.Cms.Core.PropertyEditors.IConfigurationEditor.FromConfigurationEditor(System.Collections.Generic.IDictionary{System.String,System.Object})</Target>
    <Left>lib/net7.0/Umbraco.Core.dll</Left>
    <Right>lib/net7.0/Umbraco.Core.dll</Right>
    <IsBaselineSuppression>true</IsBaselineSuppression>
  </Suppression>
  <Suppression>
    <DiagnosticId>CP0006</DiagnosticId>
    <Target>M:Umbraco.Cms.Core.PropertyEditors.IConfigurationEditor.FromConfigurationObject(System.Object,Umbraco.Cms.Core.Serialization.IConfigurationEditorJsonSerializer)</Target>
    <Left>lib/net7.0/Umbraco.Core.dll</Left>
    <Right>lib/net7.0/Umbraco.Core.dll</Right>
    <IsBaselineSuppression>true</IsBaselineSuppression>
  </Suppression>
  <Suppression>
    <DiagnosticId>CP0006</DiagnosticId>
    <Target>M:Umbraco.Cms.Core.PropertyEditors.IConfigurationEditor.ToConfigurationEditor(System.Collections.Generic.IDictionary{System.String,System.Object})</Target>
    <Left>lib/net7.0/Umbraco.Core.dll</Left>
    <Right>lib/net7.0/Umbraco.Core.dll</Right>
    <IsBaselineSuppression>true</IsBaselineSuppression>
  </Suppression>
  <Suppression>
    <DiagnosticId>CP0006</DiagnosticId>
    <Target>M:Umbraco.Cms.Core.PropertyEditors.IConfigurationEditor.ToConfigurationObject(System.Collections.Generic.IDictionary{System.String,System.Object},Umbraco.Cms.Core.Serialization.IConfigurationEditorJsonSerializer)</Target>
    <Left>lib/net7.0/Umbraco.Core.dll</Left>
    <Right>lib/net7.0/Umbraco.Core.dll</Right>
    <IsBaselineSuppression>true</IsBaselineSuppression>
  </Suppression>
  <Suppression>
    <DiagnosticId>CP0006</DiagnosticId>
    <Target>M:Umbraco.Cms.Core.PropertyEditors.IConfigurationEditor.ToDatabase(System.Collections.Generic.IDictionary{System.String,System.Object},Umbraco.Cms.Core.Serialization.IConfigurationEditorJsonSerializer)</Target>
    <Left>lib/net7.0/Umbraco.Core.dll</Left>
    <Right>lib/net7.0/Umbraco.Core.dll</Right>
    <IsBaselineSuppression>true</IsBaselineSuppression>
  </Suppression>
  <Suppression>
    <DiagnosticId>CP0006</DiagnosticId>
    <Target>M:Umbraco.Cms.Core.PropertyEditors.IConfigurationEditor.ToValueEditor(System.Collections.Generic.IDictionary{System.String,System.Object})</Target>
    <Left>lib/net7.0/Umbraco.Core.dll</Left>
    <Right>lib/net7.0/Umbraco.Core.dll</Right>
    <IsBaselineSuppression>true</IsBaselineSuppression>
  </Suppression>
  <Suppression>
    <DiagnosticId>CP0006</DiagnosticId>
    <Target>M:Umbraco.Cms.Core.PropertyEditors.IConfigurationEditor.Validate(System.Collections.Generic.IDictionary{System.String,System.Object})</Target>
    <Left>lib/net7.0/Umbraco.Core.dll</Left>
    <Right>lib/net7.0/Umbraco.Core.dll</Right>
    <IsBaselineSuppression>true</IsBaselineSuppression>
  </Suppression>
  <Suppression>
    <DiagnosticId>CP0006</DiagnosticId>
    <Target>M:Umbraco.Cms.Core.Services.IDataTypeService.CopyAsync(Umbraco.Cms.Core.Models.IDataType,System.Nullable{System.Guid},System.Guid)</Target>
    <Left>lib/net7.0/Umbraco.Core.dll</Left>
    <Right>lib/net7.0/Umbraco.Core.dll</Right>
    <IsBaselineSuppression>true</IsBaselineSuppression>
  </Suppression>
  <Suppression>
    <DiagnosticId>CP0006</DiagnosticId>
    <Target>M:Umbraco.Cms.Core.Services.IDataTypeService.CopyAsync(Umbraco.Cms.Core.Models.IDataType,System.Nullable{System.Guid},System.Int32)</Target>
    <Left>lib/net7.0/Umbraco.Core.dll</Left>
    <Right>lib/net7.0/Umbraco.Core.dll</Right>
    <IsBaselineSuppression>true</IsBaselineSuppression>
  </Suppression>
  <Suppression>
    <DiagnosticId>CP0006</DiagnosticId>
    <Target>M:Umbraco.Cms.Core.Services.IDataTypeService.CreateAsync(Umbraco.Cms.Core.Models.IDataType,System.Guid)</Target>
    <Left>lib/net7.0/Umbraco.Core.dll</Left>
    <Right>lib/net7.0/Umbraco.Core.dll</Right>
    <IsBaselineSuppression>true</IsBaselineSuppression>
  </Suppression>
  <Suppression>
    <DiagnosticId>CP0006</DiagnosticId>
    <Target>M:Umbraco.Cms.Core.Services.IDataTypeService.CreateAsync(Umbraco.Cms.Core.Models.IDataType,System.Int32)</Target>
    <Left>lib/net7.0/Umbraco.Core.dll</Left>
    <Right>lib/net7.0/Umbraco.Core.dll</Right>
    <IsBaselineSuppression>true</IsBaselineSuppression>
  </Suppression>
  <Suppression>
    <DiagnosticId>CP0006</DiagnosticId>
    <Target>M:Umbraco.Cms.Core.Services.IDataTypeService.DeleteAsync(System.Guid,System.Guid)</Target>
    <Left>lib/net7.0/Umbraco.Core.dll</Left>
    <Right>lib/net7.0/Umbraco.Core.dll</Right>
    <IsBaselineSuppression>true</IsBaselineSuppression>
  </Suppression>
  <Suppression>
    <DiagnosticId>CP0006</DiagnosticId>
    <Target>M:Umbraco.Cms.Core.Services.IDataTypeService.DeleteAsync(System.Guid,System.Int32)</Target>
    <Left>lib/net7.0/Umbraco.Core.dll</Left>
    <Right>lib/net7.0/Umbraco.Core.dll</Right>
    <IsBaselineSuppression>true</IsBaselineSuppression>
  </Suppression>
  <Suppression>
    <DiagnosticId>CP0006</DiagnosticId>
    <Target>M:Umbraco.Cms.Core.Services.IDataTypeService.GetAsync(System.Guid)</Target>
    <Left>lib/net7.0/Umbraco.Core.dll</Left>
    <Right>lib/net7.0/Umbraco.Core.dll</Right>
    <IsBaselineSuppression>true</IsBaselineSuppression>
  </Suppression>
  <Suppression>
    <DiagnosticId>CP0006</DiagnosticId>
    <Target>M:Umbraco.Cms.Core.Services.IDataTypeService.GetAsync(System.String)</Target>
    <Left>lib/net7.0/Umbraco.Core.dll</Left>
    <Right>lib/net7.0/Umbraco.Core.dll</Right>
    <IsBaselineSuppression>true</IsBaselineSuppression>
  </Suppression>
  <Suppression>
    <DiagnosticId>CP0006</DiagnosticId>
    <Target>M:Umbraco.Cms.Core.Services.IDataTypeService.GetByEditorAliasAsync(System.String)</Target>
    <Left>lib/net7.0/Umbraco.Core.dll</Left>
    <Right>lib/net7.0/Umbraco.Core.dll</Right>
    <IsBaselineSuppression>true</IsBaselineSuppression>
  </Suppression>
  <Suppression>
    <DiagnosticId>CP0006</DiagnosticId>
    <Target>M:Umbraco.Cms.Core.Services.IDataTypeService.GetReferencesAsync(System.Guid)</Target>
    <Left>lib/net7.0/Umbraco.Core.dll</Left>
    <Right>lib/net7.0/Umbraco.Core.dll</Right>
    <IsBaselineSuppression>true</IsBaselineSuppression>
  </Suppression>
  <Suppression>
    <DiagnosticId>CP0006</DiagnosticId>
    <Target>M:Umbraco.Cms.Core.Services.IDataTypeService.MoveAsync(Umbraco.Cms.Core.Models.IDataType,System.Nullable{System.Guid},System.Guid)</Target>
    <Left>lib/net7.0/Umbraco.Core.dll</Left>
    <Right>lib/net7.0/Umbraco.Core.dll</Right>
    <IsBaselineSuppression>true</IsBaselineSuppression>
  </Suppression>
  <Suppression>
    <DiagnosticId>CP0006</DiagnosticId>
    <Target>M:Umbraco.Cms.Core.Services.IDataTypeService.MoveAsync(Umbraco.Cms.Core.Models.IDataType,System.Nullable{System.Guid},System.Int32)</Target>
    <Left>lib/net7.0/Umbraco.Core.dll</Left>
    <Right>lib/net7.0/Umbraco.Core.dll</Right>
    <IsBaselineSuppression>true</IsBaselineSuppression>
  </Suppression>
  <Suppression>
    <DiagnosticId>CP0006</DiagnosticId>
    <Target>M:Umbraco.Cms.Core.Services.IDataTypeService.UpdateAsync(Umbraco.Cms.Core.Models.IDataType,System.Guid)</Target>
    <Left>lib/net7.0/Umbraco.Core.dll</Left>
    <Right>lib/net7.0/Umbraco.Core.dll</Right>
    <IsBaselineSuppression>true</IsBaselineSuppression>
  </Suppression>
  <Suppression>
    <DiagnosticId>CP0006</DiagnosticId>
    <Target>M:Umbraco.Cms.Core.Services.IDataTypeService.UpdateAsync(Umbraco.Cms.Core.Models.IDataType,System.Int32)</Target>
    <Left>lib/net7.0/Umbraco.Core.dll</Left>
    <Right>lib/net7.0/Umbraco.Core.dll</Right>
    <IsBaselineSuppression>true</IsBaselineSuppression>
  </Suppression>
  <Suppression>
    <DiagnosticId>CP0006</DiagnosticId>
    <Target>M:Umbraco.Cms.Core.Services.IDataTypeService.ValidateConfigurationData(Umbraco.Cms.Core.Models.IDataType)</Target>
    <Left>lib/net7.0/Umbraco.Core.dll</Left>
    <Right>lib/net7.0/Umbraco.Core.dll</Right>
    <IsBaselineSuppression>true</IsBaselineSuppression>
  </Suppression>
  <Suppression>
    <DiagnosticId>CP0006</DiagnosticId>
    <Target>M:Umbraco.Cms.Core.Services.IDataTypeUsageService.HasSavedValuesAsync(System.Guid)</Target>
    <Left>lib/net7.0/Umbraco.Core.dll</Left>
    <Right>lib/net7.0/Umbraco.Core.dll</Right>
    <IsBaselineSuppression>true</IsBaselineSuppression>
  </Suppression>
  <Suppression>
    <DiagnosticId>CP0006</DiagnosticId>
    <Target>M:Umbraco.Cms.Core.Services.IDomainService.GetAllAsync(System.Boolean)</Target>
    <Left>lib/net7.0/Umbraco.Core.dll</Left>
    <Right>lib/net7.0/Umbraco.Core.dll</Right>
    <IsBaselineSuppression>true</IsBaselineSuppression>
  </Suppression>
  <Suppression>
    <DiagnosticId>CP0006</DiagnosticId>
    <Target>M:Umbraco.Cms.Core.Services.IDomainService.GetAssignedDomainsAsync(System.Guid,System.Boolean)</Target>
    <Left>lib/net7.0/Umbraco.Core.dll</Left>
    <Right>lib/net7.0/Umbraco.Core.dll</Right>
    <IsBaselineSuppression>true</IsBaselineSuppression>
  </Suppression>
  <Suppression>
    <DiagnosticId>CP0006</DiagnosticId>
    <Target>M:Umbraco.Cms.Core.Services.IDomainService.UpdateDomainsAsync(System.Guid,Umbraco.Cms.Core.Models.ContentEditing.DomainsUpdateModel)</Target>
    <Left>lib/net7.0/Umbraco.Core.dll</Left>
    <Right>lib/net7.0/Umbraco.Core.dll</Right>
    <IsBaselineSuppression>true</IsBaselineSuppression>
  </Suppression>
  <Suppression>
    <DiagnosticId>CP0006</DiagnosticId>
    <Target>M:Umbraco.Cms.Core.Services.ILocalizationService.Create(System.String,System.Nullable{System.Guid},System.Collections.Generic.IEnumerable{Umbraco.Cms.Core.Models.IDictionaryTranslation},System.Int32)</Target>
    <Left>lib/net7.0/Umbraco.Core.dll</Left>
    <Right>lib/net7.0/Umbraco.Core.dll</Right>
    <IsBaselineSuppression>true</IsBaselineSuppression>
  </Suppression>
  <Suppression>
    <DiagnosticId>CP0006</DiagnosticId>
    <Target>M:Umbraco.Cms.Core.Services.ILocalizationService.Create(Umbraco.Cms.Core.Models.ILanguage,System.Int32)</Target>
    <Left>lib/net7.0/Umbraco.Core.dll</Left>
    <Right>lib/net7.0/Umbraco.Core.dll</Right>
    <IsBaselineSuppression>true</IsBaselineSuppression>
  </Suppression>
  <Suppression>
    <DiagnosticId>CP0006</DiagnosticId>
    <Target>M:Umbraco.Cms.Core.Services.ILocalizationService.Delete(System.Guid,System.Int32)</Target>
    <Left>lib/net7.0/Umbraco.Core.dll</Left>
    <Right>lib/net7.0/Umbraco.Core.dll</Right>
    <IsBaselineSuppression>true</IsBaselineSuppression>
  </Suppression>
  <Suppression>
    <DiagnosticId>CP0006</DiagnosticId>
    <Target>M:Umbraco.Cms.Core.Services.ILocalizationService.Delete(System.String,System.Int32)</Target>
    <Left>lib/net7.0/Umbraco.Core.dll</Left>
    <Right>lib/net7.0/Umbraco.Core.dll</Right>
    <IsBaselineSuppression>true</IsBaselineSuppression>
  </Suppression>
  <Suppression>
    <DiagnosticId>CP0006</DiagnosticId>
    <Target>M:Umbraco.Cms.Core.Services.ILocalizationService.Update(Umbraco.Cms.Core.Models.IDictionaryItem,System.Int32)</Target>
    <Left>lib/net7.0/Umbraco.Core.dll</Left>
    <Right>lib/net7.0/Umbraco.Core.dll</Right>
    <IsBaselineSuppression>true</IsBaselineSuppression>
  </Suppression>
  <Suppression>
    <DiagnosticId>CP0006</DiagnosticId>
    <Target>M:Umbraco.Cms.Core.Services.ILocalizationService.Update(Umbraco.Cms.Core.Models.ILanguage,System.Int32)</Target>
    <Left>lib/net7.0/Umbraco.Core.dll</Left>
    <Right>lib/net7.0/Umbraco.Core.dll</Right>
    <IsBaselineSuppression>true</IsBaselineSuppression>
  </Suppression>
  <Suppression>
    <DiagnosticId>CP0006</DiagnosticId>
    <Target>M:Umbraco.Cms.Core.Services.IMemberService.GetByKeysAsync(System.Guid[])</Target>
    <Left>lib/net7.0/Umbraco.Core.dll</Left>
    <Right>lib/net7.0/Umbraco.Core.dll</Right>
    <IsBaselineSuppression>true</IsBaselineSuppression>
  </Suppression>
  <Suppression>
    <DiagnosticId>CP0006</DiagnosticId>
    <Target>M:Umbraco.Cms.Core.Services.IPackagingService.CreateCreatedPackageAsync(Umbraco.Cms.Core.Packaging.PackageDefinition,System.Guid)</Target>
    <Left>lib/net7.0/Umbraco.Core.dll</Left>
    <Right>lib/net7.0/Umbraco.Core.dll</Right>
    <IsBaselineSuppression>true</IsBaselineSuppression>
  </Suppression>
  <Suppression>
    <DiagnosticId>CP0006</DiagnosticId>
    <Target>M:Umbraco.Cms.Core.Services.IPackagingService.CreateCreatedPackageAsync(Umbraco.Cms.Core.Packaging.PackageDefinition,System.Int32)</Target>
    <Left>lib/net7.0/Umbraco.Core.dll</Left>
    <Right>lib/net7.0/Umbraco.Core.dll</Right>
    <IsBaselineSuppression>true</IsBaselineSuppression>
  </Suppression>
  <Suppression>
    <DiagnosticId>CP0006</DiagnosticId>
    <Target>M:Umbraco.Cms.Core.Services.IPackagingService.DeleteCreatedPackageAsync(System.Guid,System.Guid)</Target>
    <Left>lib/net7.0/Umbraco.Core.dll</Left>
    <Right>lib/net7.0/Umbraco.Core.dll</Right>
    <IsBaselineSuppression>true</IsBaselineSuppression>
  </Suppression>
  <Suppression>
    <DiagnosticId>CP0006</DiagnosticId>
    <Target>M:Umbraco.Cms.Core.Services.IPackagingService.DeleteCreatedPackageAsync(System.Guid,System.Int32)</Target>
    <Left>lib/net7.0/Umbraco.Core.dll</Left>
    <Right>lib/net7.0/Umbraco.Core.dll</Right>
    <IsBaselineSuppression>true</IsBaselineSuppression>
  </Suppression>
  <Suppression>
    <DiagnosticId>CP0006</DiagnosticId>
    <Target>M:Umbraco.Cms.Core.Services.IPackagingService.GetCreatedPackageByKey(System.Guid)</Target>
    <Left>lib/net7.0/Umbraco.Core.dll</Left>
    <Right>lib/net7.0/Umbraco.Core.dll</Right>
    <IsBaselineSuppression>true</IsBaselineSuppression>
  </Suppression>
  <Suppression>
    <DiagnosticId>CP0006</DiagnosticId>
    <Target>M:Umbraco.Cms.Core.Services.IPackagingService.GetCreatedPackageByKeyAsync(System.Guid)</Target>
    <Left>lib/net7.0/Umbraco.Core.dll</Left>
    <Right>lib/net7.0/Umbraco.Core.dll</Right>
    <IsBaselineSuppression>true</IsBaselineSuppression>
  </Suppression>
  <Suppression>
    <DiagnosticId>CP0006</DiagnosticId>
    <Target>M:Umbraco.Cms.Core.Services.IPackagingService.GetInstalledPackagesFromMigrationPlans</Target>
    <Left>lib/net7.0/Umbraco.Core.dll</Left>
    <Right>lib/net7.0/Umbraco.Core.dll</Right>
    <IsBaselineSuppression>true</IsBaselineSuppression>
  </Suppression>
  <Suppression>
    <DiagnosticId>CP0006</DiagnosticId>
    <Target>M:Umbraco.Cms.Core.Services.IPackagingService.GetInstalledPackagesFromMigrationPlansAsync(System.Int32,System.Int32)</Target>
    <Left>lib/net7.0/Umbraco.Core.dll</Left>
    <Right>lib/net7.0/Umbraco.Core.dll</Right>
    <IsBaselineSuppression>true</IsBaselineSuppression>
  </Suppression>
  <Suppression>
    <DiagnosticId>CP0006</DiagnosticId>
    <Target>M:Umbraco.Cms.Core.Services.IPackagingService.UpdateCreatedPackageAsync(Umbraco.Cms.Core.Packaging.PackageDefinition,System.Guid)</Target>
    <Left>lib/net7.0/Umbraco.Core.dll</Left>
    <Right>lib/net7.0/Umbraco.Core.dll</Right>
    <IsBaselineSuppression>true</IsBaselineSuppression>
  </Suppression>
  <Suppression>
    <DiagnosticId>CP0006</DiagnosticId>
    <Target>M:Umbraco.Cms.Core.Services.IPackagingService.UpdateCreatedPackageAsync(Umbraco.Cms.Core.Packaging.PackageDefinition,System.Int32)</Target>
    <Left>lib/net7.0/Umbraco.Core.dll</Left>
    <Right>lib/net7.0/Umbraco.Core.dll</Right>
    <IsBaselineSuppression>true</IsBaselineSuppression>
  </Suppression>
  <Suppression>
    <DiagnosticId>CP0006</DiagnosticId>
    <Target>M:Umbraco.Cms.Core.Services.IPropertyTypeUsageService.HasSavedPropertyValuesAsync(System.Guid,System.String)</Target>
    <Left>lib/net7.0/Umbraco.Core.dll</Left>
    <Right>lib/net7.0/Umbraco.Core.dll</Right>
    <IsBaselineSuppression>true</IsBaselineSuppression>
  </Suppression>
  <Suppression>
    <DiagnosticId>CP0006</DiagnosticId>
    <Target>M:Umbraco.Cms.Core.Services.IRelationService.CreateAsync(Umbraco.Cms.Core.Models.IRelationType,System.Guid)</Target>
    <Left>lib/net7.0/Umbraco.Core.dll</Left>
    <Right>lib/net7.0/Umbraco.Core.dll</Right>
    <IsBaselineSuppression>true</IsBaselineSuppression>
  </Suppression>
  <Suppression>
    <DiagnosticId>CP0006</DiagnosticId>
    <Target>M:Umbraco.Cms.Core.Services.IRelationService.DeleteAsync(System.Guid,System.Guid)</Target>
    <Left>lib/net7.0/Umbraco.Core.dll</Left>
    <Right>lib/net7.0/Umbraco.Core.dll</Right>
    <IsBaselineSuppression>true</IsBaselineSuppression>
  </Suppression>
  <Suppression>
    <DiagnosticId>CP0006</DiagnosticId>
    <Target>M:Umbraco.Cms.Core.Services.IRelationService.GetAllowedObjectTypes</Target>
    <Left>lib/net7.0/Umbraco.Core.dll</Left>
    <Right>lib/net7.0/Umbraco.Core.dll</Right>
    <IsBaselineSuppression>true</IsBaselineSuppression>
  </Suppression>
  <Suppression>
    <DiagnosticId>CP0006</DiagnosticId>
    <Target>M:Umbraco.Cms.Core.Services.IRelationService.GetPagedByRelationTypeKey(System.Guid,System.Int32,System.Int32,Umbraco.Cms.Core.Services.Ordering)</Target>
    <Left>lib/net7.0/Umbraco.Core.dll</Left>
    <Right>lib/net7.0/Umbraco.Core.dll</Right>
    <IsBaselineSuppression>true</IsBaselineSuppression>
  </Suppression>
  <Suppression>
    <DiagnosticId>CP0006</DiagnosticId>
    <Target>M:Umbraco.Cms.Core.Services.IRelationService.UpdateAsync(Umbraco.Cms.Core.Models.IRelationType,System.Guid)</Target>
    <Left>lib/net7.0/Umbraco.Core.dll</Left>
    <Right>lib/net7.0/Umbraco.Core.dll</Right>
    <IsBaselineSuppression>true</IsBaselineSuppression>
  </Suppression>
  <Suppression>
    <DiagnosticId>CP0006</DiagnosticId>
    <Target>M:Umbraco.Cms.Core.Services.ITrackedReferencesService.GetPagedDescendantsInReferencesAsync(System.Guid,System.Int64,System.Int64,System.Boolean)</Target>
    <Left>lib/net7.0/Umbraco.Core.dll</Left>
    <Right>lib/net7.0/Umbraco.Core.dll</Right>
    <IsBaselineSuppression>true</IsBaselineSuppression>
  </Suppression>
  <Suppression>
    <DiagnosticId>CP0006</DiagnosticId>
    <Target>M:Umbraco.Cms.Core.Services.ITrackedReferencesService.GetPagedItemsWithRelationsAsync(System.Collections.Generic.ISet{System.Guid},System.Int64,System.Int64,System.Boolean)</Target>
    <Left>lib/net7.0/Umbraco.Core.dll</Left>
    <Right>lib/net7.0/Umbraco.Core.dll</Right>
    <IsBaselineSuppression>true</IsBaselineSuppression>
  </Suppression>
  <Suppression>
    <DiagnosticId>CP0006</DiagnosticId>
    <Target>M:Umbraco.Cms.Core.Services.ITrackedReferencesService.GetPagedRelationsForItemAsync(System.Guid,System.Int64,System.Int64,System.Boolean)</Target>
    <Left>lib/net7.0/Umbraco.Core.dll</Left>
    <Right>lib/net7.0/Umbraco.Core.dll</Right>
    <IsBaselineSuppression>true</IsBaselineSuppression>
  </Suppression>
  <Suppression>
    <DiagnosticId>CP0006</DiagnosticId>
    <Target>M:Umbraco.Cms.Core.Services.IUserService.ChangePasswordAsync(System.Guid,Umbraco.Cms.Core.Models.Membership.ChangeBackofficeUserPasswordModel)</Target>
    <Left>lib/net7.0/Umbraco.Core.dll</Left>
    <Right>lib/net7.0/Umbraco.Core.dll</Right>
    <IsBaselineSuppression>true</IsBaselineSuppression>
  </Suppression>
  <Suppression>
    <DiagnosticId>CP0006</DiagnosticId>
    <Target>M:Umbraco.Cms.Core.Services.IUserService.ChangePasswordAsync(System.Guid,Umbraco.Cms.Core.Models.Membership.ChangeUserPasswordModel)</Target>
    <Left>lib/net7.0/Umbraco.Core.dll</Left>
    <Right>lib/net7.0/Umbraco.Core.dll</Right>
    <IsBaselineSuppression>true</IsBaselineSuppression>
  </Suppression>
  <Suppression>
    <DiagnosticId>CP0006</DiagnosticId>
    <Target>M:Umbraco.Cms.Core.Services.IUserService.ClearAvatarAsync(System.Guid)</Target>
    <Left>lib/net7.0/Umbraco.Core.dll</Left>
    <Right>lib/net7.0/Umbraco.Core.dll</Right>
    <IsBaselineSuppression>true</IsBaselineSuppression>
  </Suppression>
  <Suppression>
    <DiagnosticId>CP0006</DiagnosticId>
    <Target>M:Umbraco.Cms.Core.Services.IUserService.CreateAsync(System.Guid,Umbraco.Cms.Core.Models.UserCreateModel,System.Boolean)</Target>
    <Left>lib/net7.0/Umbraco.Core.dll</Left>
    <Right>lib/net7.0/Umbraco.Core.dll</Right>
    <IsBaselineSuppression>true</IsBaselineSuppression>
  </Suppression>
  <Suppression>
    <DiagnosticId>CP0006</DiagnosticId>
    <Target>M:Umbraco.Cms.Core.Services.IUserService.DeleteAsync(System.Guid)</Target>
    <Left>lib/net7.0/Umbraco.Core.dll</Left>
    <Right>lib/net7.0/Umbraco.Core.dll</Right>
    <IsBaselineSuppression>true</IsBaselineSuppression>
  </Suppression>
  <Suppression>
    <DiagnosticId>CP0006</DiagnosticId>
    <Target>M:Umbraco.Cms.Core.Services.IUserService.DisableAsync(System.Guid,System.Collections.Generic.ISet{System.Guid})</Target>
    <Left>lib/net7.0/Umbraco.Core.dll</Left>
    <Right>lib/net7.0/Umbraco.Core.dll</Right>
    <IsBaselineSuppression>true</IsBaselineSuppression>
  </Suppression>
  <Suppression>
    <DiagnosticId>CP0006</DiagnosticId>
    <Target>M:Umbraco.Cms.Core.Services.IUserService.DisableAsync(System.Guid,System.Guid[])</Target>
    <Left>lib/net7.0/Umbraco.Core.dll</Left>
    <Right>lib/net7.0/Umbraco.Core.dll</Right>
    <IsBaselineSuppression>true</IsBaselineSuppression>
  </Suppression>
  <Suppression>
    <DiagnosticId>CP0006</DiagnosticId>
    <Target>M:Umbraco.Cms.Core.Services.IUserService.EnableAsync(System.Guid,System.Collections.Generic.ISet{System.Guid})</Target>
    <Left>lib/net7.0/Umbraco.Core.dll</Left>
    <Right>lib/net7.0/Umbraco.Core.dll</Right>
    <IsBaselineSuppression>true</IsBaselineSuppression>
  </Suppression>
  <Suppression>
    <DiagnosticId>CP0006</DiagnosticId>
    <Target>M:Umbraco.Cms.Core.Services.IUserService.EnableAsync(System.Guid,System.Guid[])</Target>
    <Left>lib/net7.0/Umbraco.Core.dll</Left>
    <Right>lib/net7.0/Umbraco.Core.dll</Right>
    <IsBaselineSuppression>true</IsBaselineSuppression>
  </Suppression>
  <Suppression>
    <DiagnosticId>CP0006</DiagnosticId>
    <Target>M:Umbraco.Cms.Core.Services.IUserService.InviteAsync(System.Guid,Umbraco.Cms.Core.Models.UserInviteModel)</Target>
    <Left>lib/net7.0/Umbraco.Core.dll</Left>
    <Right>lib/net7.0/Umbraco.Core.dll</Right>
    <IsBaselineSuppression>true</IsBaselineSuppression>
  </Suppression>
  <Suppression>
    <DiagnosticId>CP0006</DiagnosticId>
    <Target>M:Umbraco.Cms.Core.Services.IUserService.SetAvatarAsync(System.Guid,System.Guid)</Target>
    <Left>lib/net7.0/Umbraco.Core.dll</Left>
    <Right>lib/net7.0/Umbraco.Core.dll</Right>
    <IsBaselineSuppression>true</IsBaselineSuppression>
  </Suppression>
  <Suppression>
    <DiagnosticId>CP0006</DiagnosticId>
    <Target>M:Umbraco.Cms.Core.Services.IUserService.SetAvatarAsync(Umbraco.Cms.Core.Models.Membership.IUser,System.Guid)</Target>
    <Left>lib/net7.0/Umbraco.Core.dll</Left>
    <Right>lib/net7.0/Umbraco.Core.dll</Right>
    <IsBaselineSuppression>true</IsBaselineSuppression>
  </Suppression>
  <Suppression>
    <DiagnosticId>CP0006</DiagnosticId>
    <Target>M:Umbraco.Cms.Core.Services.IUserService.UnlockAsync(System.Guid,System.Guid[])</Target>
    <Left>lib/net7.0/Umbraco.Core.dll</Left>
    <Right>lib/net7.0/Umbraco.Core.dll</Right>
    <IsBaselineSuppression>true</IsBaselineSuppression>
  </Suppression>
  <Suppression>
    <DiagnosticId>CP0006</DiagnosticId>
    <Target>M:Umbraco.Cms.Core.Services.IUserService.UpdateAsync(System.Guid,Umbraco.Cms.Core.Models.UserUpdateModel)</Target>
    <Left>lib/net7.0/Umbraco.Core.dll</Left>
    <Right>lib/net7.0/Umbraco.Core.dll</Right>
    <IsBaselineSuppression>true</IsBaselineSuppression>
  </Suppression>
  <Suppression>
    <DiagnosticId>CP0006</DiagnosticId>
    <Target>M:Umbraco.Cms.Core.Telemetry.ITelemetryService.GetTelemetryReportDataAsync</Target>
    <Left>lib/net7.0/Umbraco.Core.dll</Left>
    <Right>lib/net7.0/Umbraco.Core.dll</Right>
    <IsBaselineSuppression>true</IsBaselineSuppression>
  </Suppression>
  <Suppression>
    <DiagnosticId>CP0006</DiagnosticId>
    <Target>P:Umbraco.Cms.Core.Models.IDataType.ConfigurationData</Target>
    <Left>lib/net7.0/Umbraco.Core.dll</Left>
    <Right>lib/net7.0/Umbraco.Core.dll</Right>
    <IsBaselineSuppression>true</IsBaselineSuppression>
  </Suppression>
  <Suppression>
    <DiagnosticId>CP0006</DiagnosticId>
    <Target>P:Umbraco.Cms.Core.Models.IDataType.ConfigurationObject</Target>
    <Left>lib/net7.0/Umbraco.Core.dll</Left>
    <Right>lib/net7.0/Umbraco.Core.dll</Right>
    <IsBaselineSuppression>true</IsBaselineSuppression>
  </Suppression>
  <Suppression>
    <DiagnosticId>CP0006</DiagnosticId>
    <Target>P:Umbraco.Cms.Core.Models.IDataType.EditorUiAlias</Target>
    <Left>lib/net7.0/Umbraco.Core.dll</Left>
    <Right>lib/net7.0/Umbraco.Core.dll</Right>
    <IsBaselineSuppression>true</IsBaselineSuppression>
  </Suppression>
  <Suppression>
    <DiagnosticId>CP0006</DiagnosticId>
    <Target>P:Umbraco.Cms.Core.Models.IDictionaryTranslation.LanguageIsoCode</Target>
    <Left>lib/net7.0/Umbraco.Core.dll</Left>
    <Right>lib/net7.0/Umbraco.Core.dll</Right>
    <IsBaselineSuppression>true</IsBaselineSuppression>
  </Suppression>
  <Suppression>
    <DiagnosticId>CP0006</DiagnosticId>
    <Target>P:Umbraco.Cms.Core.Models.ILanguage.FallbackIsoCode</Target>
    <Left>lib/net7.0/Umbraco.Core.dll</Left>
    <Right>lib/net7.0/Umbraco.Core.dll</Right>
    <IsBaselineSuppression>true</IsBaselineSuppression>
  </Suppression>
  <Suppression>
    <DiagnosticId>CP0006</DiagnosticId>
    <Target>P:Umbraco.Cms.Core.Models.Membership.IUserGroup.PermissionNames</Target>
    <Left>lib/net7.0/Umbraco.Core.dll</Left>
    <Right>lib/net7.0/Umbraco.Core.dll</Right>
    <IsBaselineSuppression>true</IsBaselineSuppression>
  </Suppression>
  <Suppression>
    <DiagnosticId>CP0006</DiagnosticId>
    <Target>P:Umbraco.Cms.Core.Models.PublishedContent.IPublishedPropertyType.DeliveryApiCacheLevel</Target>
    <Left>lib/net7.0/Umbraco.Core.dll</Left>
    <Right>lib/net7.0/Umbraco.Core.dll</Right>
    <IsBaselineSuppression>true</IsBaselineSuppression>
  </Suppression>
  <Suppression>
    <DiagnosticId>CP0006</DiagnosticId>
    <Target>P:Umbraco.Cms.Core.Scoping.ICoreScope.Locks</Target>
    <Left>lib/net7.0/Umbraco.Core.dll</Left>
    <Right>lib/net7.0/Umbraco.Core.dll</Right>
    <IsBaselineSuppression>true</IsBaselineSuppression>
  </Suppression>
  <Suppression>
    <DiagnosticId>CP0007</DiagnosticId>
    <Target>T:Umbraco.Cms.Core.Notifications.MovedToRecycleBinNotification`1</Target>
    <Left>lib/net7.0/Umbraco.Core.dll</Left>
    <Right>lib/net7.0/Umbraco.Core.dll</Right>
    <IsBaselineSuppression>true</IsBaselineSuppression>
  </Suppression>
  <Suppression>
    <DiagnosticId>CP0007</DiagnosticId>
    <Target>T:Umbraco.Cms.Core.Notifications.MovingToRecycleBinNotification`1</Target>
    <Left>lib/net7.0/Umbraco.Core.dll</Left>
    <Right>lib/net7.0/Umbraco.Core.dll</Right>
    <IsBaselineSuppression>true</IsBaselineSuppression>
  </Suppression>
  <Suppression>
    <DiagnosticId>CP0008</DiagnosticId>
    <Target>T:Umbraco.Cms.Core.Events.MoveEventInfo`1</Target>
    <Left>lib/net7.0/Umbraco.Core.dll</Left>
    <Right>lib/net7.0/Umbraco.Core.dll</Right>
    <IsBaselineSuppression>true</IsBaselineSuppression>
  </Suppression>
</Suppressions>